{
  "2026-03-29_ST_3": {
    "race_id": "2026-03-29_ST_3",
    "race_date": "2026-03-29",
    "race_number": 3,
    "venue": "Sha Tin",
    "distance": 1200,
    "race_class": "Class 3",
    "going": "Good to Firm",
    "predicted_top3": [
      5,
      2,
      11
    ],
    "predicted_winner": 5,
    "predicted_winner_odds": 4.8,
    "predicted_top3_odds": [
      4.8,
      7.199999999999999,
      10.56
    ],
    "actual_result": [
      7,
      8,
      10,
      1,
      5,
      4,
      12,
      9,
      2,
      3
    ],
    "actual_winner": 7,
    "winner_correct": false,
    "top3_hit": 0,
    "trio_hit": false,
    "win_bet_return": 0.0,
    "place_bet_return": 0.0,
    "trio_bet_return": 0.0,
    "model_confidence": 0.71,
    "is_real_result": true,
    "created_at": "2026-04-03T11:45:53.467335",
    "result_recorded_at": "2026-04-03T12:27:34.014934"
  },
  "2026-03-29_ST_6": {
    "race_id": "2026-03-29_ST_6",
    "race_date": "2026-03-29",
    "race_number": 6,
    "venue": "Sha Tin",
    "distance": 1600,
    "race_class": "Class 2",
    "going": "Good to Firm",
    "predicted_top3": [
      3,
      8,
      1
    ],
    "predicted_winner": 3,
    "predicted_winner_odds": 7.2,
    "predicted_top3_odds": [
      7.2,
      10.8,
      15.840000000000002
    ],
    "actual_result": [
      8,
      7,
      3,
      4,
      14,
      12,
      11,
      2,
      1,
      5
    ],
    "actual_winner": 8,
    "winner_correct": false,
    "top3_hit": 2,
    "trio_hit": false,
    "win_bet_return": 0.0,
    "place_bet_return": 20.0,
    "trio_bet_return": 0.0,
    "model_confidence": 0.58,
    "is_real_result": true,
    "created_at": "2026-04-03T11:45:53.467335",
    "result_recorded_at": "2026-04-03T12:27:34.014934"
  },
  "2026-03-29_ST_9": {
    "race_id": "2026-03-29_ST_9",
    "race_date": "2026-03-29",
    "race_number": 9,
    "venue": "Sha Tin",
    "distance": 2000,
    "race_class": "Class 1",
    "going": "Good",
    "predicted_top3": [
      1,
      4,
      7
    ],
    "predicted_winner": 1,
    "predicted_winner_odds": 6.5,
    "predicted_top3_odds": [
      6.5,
      9.75,
      14.3
    ],
    "actual_result": [
      9,
      4,
      7,
      3,
      11,
      10,
      8,
      1,
      6,
      5
    ],
    "actual_winner": 9,
    "winner_correct": false,
    "top3_hit": 2,
    "trio_hit": false,
    "win_bet_return": 0.0,
    "place_bet_return": 0.0,
    "trio_bet_return": 0.0,
    "model_confidence": 0.54,
    "is_real_result": true,
    "created_at": "2026-04-03T11:45:53.467335",
    "result_recorded_at": "2026-04-03T12:27:34.014934"
  },
  "2026-03-25_HV_2": {
    "race_id": "2026-03-25_HV_2",
    "race_date": "2026-03-25",
    "race_number": 2,
    "venue": "Happy Valley",
    "distance": 1000,
    "race_class": "Class 4",
    "going": "Good",
    "predicted_top3": [
      6,
      3,
      9
    ],
    "predicted_winner": 6,
    "predicted_winner_odds": 5.5,
    "predicted_top3_odds": [
      5.5,
      8.25,
      12.100000000000001
    ],
    "actual_result": [
      3,
      9,
      12,
      11,
      10,
      4,
      1,
      8,
      5,
      7
    ],
    "actual_winner": 3,
    "winner_correct": false,
    "top3_hit": 2,
    "trio_hit": false,
    "win_bet_return": 0.0,
    "place_bet_return": 0.0,
    "trio_bet_return": 0.0,
    "model_confidence": 0.66,
    "is_real_result": true,
    "created_at": "2026-04-03T11:45:53.468228",
    "result_recorded_at": "2026-04-03T12:27:34.014934"
  },
  "2026-03-25_HV_5": {
    "race_id": "2026-03-25_HV_5",
    "race_date": "2026-03-25",
    "race_number": 5,
    "venue": "Happy Valley",
    "distance": 1650,
    "race_class": "Class 3",
    "going": "Good",
    "predicted_top3": [
      2,
      7,
      4
    ],
    "predicted_winner": 2,
    "predicted_winner_odds": 9.0,
    "predicted_top3_odds": [
      9.0,
      13.5,
      19.8
    ],
    "actual_result": [
      12,
      1,
      3,
      6,
      2,
      5,
      4,
      11,
      7,
      8
    ],
    "actual_winner": 12,
    "winner_correct": false,
    "top3_hit": 0,
    "trio_hit": false,
    "win_bet_return": 0.0,
    "place_bet_return": 0.0,
    "trio_bet_return": 0.0,
    "model_confidence": 0.52,
    "is_real_result": true,
    "created_at": "2026-04-03T11:45:53.468228",
    "result_recorded_at": "2026-04-03T12:27:34.014934"
  },
  "2026-03-22_ST_1": {
    "race_id": "2026-03-22_ST_1",
    "race_date": "2026-03-22",
    "race_number": 1,
    "venue": "Sha Tin",
    "distance": 1000,
    "race_class": "Class 5",
    "going": "Firm",
    "predicted_top3": [
      9,
      4,
      2
    ],
    "predicted_winner": 9,
    "predicted_winner_odds": 3.9,
    "predicted_top3_odds": [
      3.9,
      5.85,
      8.58
    ],
    "actual_result": [
      8,
      10,
      6,
      9,
      1,
      3,
      12,
      4,
      13,
      14
    ],
    "actual_winner": 8,
    "winner_correct": false,
    "top3_hit": 0,
    "trio_hit": false,
    "win_bet_return": 0.0,
    "place_bet_return": 0.0,
    "trio_bet_return": 0.0,
    "model_confidence": 0.74,
    "is_real_result": true,
    "created_at": "2026-04-03T11:45:53.468228",
    "result_recorded_at": "2026-04-03T12:27:34.014934"
  },
  "2026-03-22_ST_4": {
    "race_id": "2026-03-22_ST_4",
    "race_date": "2026-03-22",
    "race_number": 4,
    "venue": "Sha Tin",
    "distance": 1400,
    "race_class": "Class 4",
    "going": "Firm",
    "predicted_top3": [
      7,
      1,
      5
    ],
    "predicted_winner": 7,
    "predicted_winner_odds": 11.0,
    "predicted_top3_odds": [
      11.0,
      16.5,
      24.200000000000003
    ],
    "actual_result": [
      3,
      6,
      13,
      7,
      2,
      11,
      4,
      5,
      14,
      10
    ],
    "actual_winner": 3,
    "winner_correct": false,
    "top3_hit": 0,
    "trio_hit": false,
    "win_bet_return": 0.0,
    "place_bet_return": 0.0,
    "trio_bet_return": 0.0,
    "model_confidence": 0.49,
    "is_real_result": true,
    "created_at": "2026-04-03T11:45:53.468228",
    "result_recorded_at": "2026-04-03T12:27:34.014934"
  },
  "2026-03-22_ST_8": {
    "race_id": "2026-03-22_ST_8",
    "race_date": "2026-03-22",
    "race_number": 8,
    "venue": "Sha Tin",
    "distance": 1800,
    "race_class": "Class 3",
    "going": "Firm",
    "predicted_top3": [
      3,
      6,
      10
    ],
    "predicted_winner": 3,
    "predicted_winner_odds": 6.0,
    "predicted_top3_odds": [
      6.0,
      9.0,
      13.200000000000001
    ],
    "actual_result": [
      13,
      6,
      5,
      3,
      10,
      11,
      12,
      7,
      8,
      4
    ],
    "actual_winner": 13,
    "winner_correct": false,
    "top3_hit": 1,
    "trio_hit": false,
    "win_bet_return": 0.0,
    "place_bet_return": 0.0,
    "trio_bet_return": 0.0,
    "model_confidence": 0.68,
    "is_real_result": true,
    "created_at": "2026-04-03T11:45:53.468228",
    "result_recorded_at": "2026-04-03T12:27:34.014934"
  },
  "2026-03-18_HV_3": {
    "race_id": "2026-03-18_HV_3",
    "race_date": "2026-03-18",
    "race_number": 3,
    "venue": "Happy Valley",
    "distance": 1200,
    "race_class": "Class 4",
    "going": "Good",
    "predicted_top3": [
      4,
      8,
      2
    ],
    "predicted_winner": 4,
    "predicted_winner_odds": 8.5,
    "predicted_top3_odds": [
      8.5,
      12.75,
      18.700000000000003
    ],
    "actual_result": [
      5,
      3,
      11,
      9,
      10,
      12,
      4,
      7,
      8,
      2
    ],
    "actual_winner": 5,
    "winner_correct": false,
    "top3_hit": 0,
    "trio_hit": false,
    "win_bet_return": 0.0,
    "place_bet_return": 0.0,
    "trio_bet_return": 0.0,
    "model_confidence": 0.55,
    "is_real_result": true,
    "created_at": "2026-04-03T11:45:53.468228",
    "result_recorded_at": "2026-04-03T12:27:34.014934"
  },
  "2026-03-18_HV_7": {
    "race_id": "2026-03-18_HV_7",
    "race_date": "2026-03-18",
    "race_number": 7,
    "venue": "Happy Valley",
    "distance": 1650,
    "race_class": "Class 3",
    "going": "Good",
    "predicted_top3": [
      1,
      5,
      9
    ],
    "predicted_winner": 1,
    "predicted_winner_odds": 5.0,
    "predicted_top3_odds": [
      5.0,
      7.5,
      11.0
    ],
    "actual_result": [
      6,
      4,
      8,
      7,
      10,
      1,
      5,
      3,
      2,
      9
    ],
    "actual_winner": 6,
    "winner_correct": false,
    "top3_hit": 0,
    "trio_hit": false,
    "win_bet_return": 0.0,
    "place_bet_return": 0.0,
    "trio_bet_return": 0.0,
    "model_confidence": 0.62,
    "is_real_result": true,
    "created_at": "2026-04-03T11:45:53.468228",
    "result_recorded_at": "2026-04-03T12:27:34.014934"
  },
  "2026-03-15_ST_2": {
    "race_id": "2026-03-15_ST_2",
    "race_date": "2026-03-15",
    "race_number": 2,
    "venue": "Sha Tin",
    "distance": 1200,
    "race_class": "Class 3",
    "going": "Good to Firm",
    "predicted_top3": [
      6,
      3,
      11
    ],
    "predicted_winner": 6,
    "predicted_winner_odds": 12.0,
    "predicted_top3_odds": [
      12.0,
      18.0,
      26.400000000000002
    ],
    "actual_result": [
      9,
      8,
      3,
      7,
      6,
      5,
      12,
      2,
      11,
      4
    ],
    "actual_winner": 9,
    "winner_correct": false,
    "top3_hit": 1,
    "trio_hit": false,
    "win_bet_return": 0.0,
    "place_bet_return": 0.0,
    "trio_bet_return": 0.0,
    "model_confidence": 0.6,
    "is_real_result": true,
    "created_at": "2026-04-03T11:45:53.468228",
    "result_recorded_at": "2026-04-03T12:27:34.014934"
  },
  "2026-03-15_ST_5": {
    "race_id": "2026-03-15_ST_5",
    "race_date": "2026-03-15",
    "race_number": 5,
    "venue": "Sha Tin",
    "distance": 1600,
    "race_class": "Class 4",
    "going": "Good to Firm",
    "predicted_top3": [
      2,
      9,
      5
    ],
    "predicted_winner": 2,
    "predicted_winner_odds": 4.2,
    "predicted_top3_odds": [
      4.2,
      6.300000000000001,
      9.240000000000002
    ],
    "actual_result": [
      1,
      5,
      11,
      10,
      6,
      7,
      8,
      13,
      12,
      3
    ],
    "actual_winner": 1,
    "winner_correct": false,
    "top3_hit": 1,
    "trio_hit": false,
    "win_bet_return": 0.0,
    "place_bet_return": 0.0,
    "trio_bet_return": 0.0,
    "model_confidence": 0.59,
    "is_real_result": true,
    "created_at": "2026-04-03T11:45:53.468228",
    "result_recorded_at": "2026-04-03T12:27:34.014934"
  },
  "2026-03-15_ST_9": {
    "race_id": "2026-03-15_ST_9",
    "race_date": "2026-03-15",
    "race_number": 9,
    "venue": "Sha Tin",
    "distance": 2200,
    "race_class": "Class 2",
    "going": "Good",
    "predicted_top3": [
      8,
      1,
      4
    ],
    "predicted_winner": 8,
    "predicted_winner_odds": 7.8,
    "predicted_top3_odds": [
      7.8,
      11.7,
      17.16
    ],
    "actual_result": [
      5,
      3,
      13,
      10,
      9,
      14,
      12,
      1,
      7,
      11
    ],
    "actual_winner": 5,
    "winner_correct": false,
    "top3_hit": 0,
    "trio_hit": false,
    "win_bet_return": 0.0,
    "place_bet_return": 0.0,
    "trio_bet_return": 0.0,
    "model_confidence": 0.57,
    "is_real_result": true,
    "created_at": "2026-04-03T11:45:53.468228",
    "result_recorded_at": "2026-04-03T12:27:34.014934"
  },
  "2026-03-11_HV_1": {
    "race_id": "2026-03-11_HV_1",
    "race_date": "2026-03-11",
    "race_number": 1,
    "venue": "Happy Valley",
    "distance": 1000,
    "race_class": "Class 5",
    "going": "Good",
    "predicted_top3": [
      5,
      2,
      7
    ],
    "predicted_winner": 5,
    "predicted_winner_odds": 6.5,
    "predicted_top3_odds": [
      6.5,
      9.75,
      14.3
    ],
    "actual_result": [
      1,
      9,
      6,
      8,
      7,
      10,
      5,
      4,
      2,
      12
    ],
    "actual_winner": 1,
    "winner_correct": false,
    "top3_hit": 0,
    "trio_hit": false,
    "win_bet_return": 0.0,
    "place_bet_return": 0.0,
    "trio_bet_return": 0.0,
    "model_confidence": 0.64,
    "is_real_result": true,
    "created_at": "2026-04-03T11:45:53.468228",
    "result_recorded_at": "2026-04-03T12:27:34.014934"
  },
  "2026-03-11_HV_4": {
    "race_id": "2026-03-11_HV_4",
    "race_date": "2026-03-11",
    "race_number": 4,
    "venue": "Happy Valley",
    "distance": 1200,
    "race_class": "Class 4",
    "going": "Good",
    "predicted_top3": [
      3,
      6,
      1
    ],
    "predicted_winner": 3,
    "predicted_winner_odds": 9.5,
    "predicted_top3_odds": [
      9.5,
      14.25,
      20.900000000000002
    ],
    "actual_result": [
      6,
      10,
      1,
      7,
      3,
      11,
      4,
      8,
      9,
      12
    ],
    "actual_winner": 6,
    "winner_correct": false,
    "top3_hit": 2,
    "trio_hit": false,
    "win_bet_return": 0.0,
    "place_bet_return": 0.0,
    "trio_bet_return": 0.0,
    "model_confidence": 0.5,
    "is_real_result": true,
    "created_at": "2026-04-03T11:45:53.468228",
    "result_recorded_at": "2026-04-03T12:27:34.014934"
  },
  "2026-03-08_ST_3": {
    "race_id": "2026-03-08_ST_3",
    "race_date": "2026-03-08",
    "race_number": 3,
    "venue": "Sha Tin",
    "distance": 1400,
    "race_class": "Class 4",
    "going": "Good",
    "predicted_top3": [
      10,
      4,
      7
    ],
    "predicted_winner": 10,
    "predicted_winner_odds": 5.5,
    "predicted_top3_odds": [
      5.5,
      8.25,
      12.100000000000001
    ],
    "actual_result": [
      11,
      8,
      12,
      10,
      2,
      9,
      7,
      4,
      1,
      5
    ],
    "actual_winner": 11,
    "winner_correct": false,
    "top3_hit": 0,
    "trio_hit": false,
    "win_bet_return": 0.0,
    "place_bet_return": 0.0,
    "trio_bet_return": 0.0,
    "model_confidence": 0.69,
    "is_real_result": true,
    "created_at": "2026-04-03T11:45:53.468228",
    "result_recorded_at": "2026-04-03T12:27:34.014934"
  },
  "2026-03-08_ST_6": {
    "race_id": "2026-03-08_ST_6",
    "race_date": "2026-03-08",
    "race_number": 6,
    "venue": "Sha Tin",
    "distance": 1600,
    "race_class": "Class 3",
    "going": "Good",
    "predicted_top3": [
      1,
      8,
      3
    ],
    "predicted_winner": 1,
    "predicted_winner_odds": 8.0,
    "predicted_top3_odds": [
      8.0,
      12.0,
      17.6
    ],
    "actual_result": [
      2,
      1,
      7,
      12,
      5,
      10,
      6,
      11,
      3,
      8
    ],
    "actual_winner": 2,
    "winner_correct": false,
    "top3_hit": 1,
    "trio_hit": false,
    "win_bet_return": 0.0,
    "place_bet_return": 20.0,
    "trio_bet_return": 0.0,
    "model_confidence": 0.53,
    "is_real_result": true,
    "created_at": "2026-04-03T11:45:53.468228",
    "result_recorded_at": "2026-04-03T12:27:34.014934"
  },
  "2026-03-08_ST_9": {
    "race_id": "2026-03-08_ST_9",
    "race_date": "2026-03-08",
    "race_number": 9,
    "venue": "Sha Tin",
    "distance": 2000,
    "race_class": "Class 2",
    "going": "Good",
    "predicted_top3": [
      2,
      6,
      9
    ],
    "predicted_winner": 2,
    "predicted_winner_odds": 6.8,
    "predicted_top3_odds": [
      6.8,
      10.2,
      14.96
    ],
    "actual_result": [
      9,
      7,
      6,
      3,
      1,
      12,
      14,
      5,
      2,
      8
    ],
    "actual_winner": 9,
    "winner_correct": false,
    "top3_hit": 2,
    "trio_hit": false,
    "win_bet_return": 0.0,
    "place_bet_return": 0.0,
    "trio_bet_return": 0.0,
    "model_confidence": 0.72,
    "is_real_result": true,
    "created_at": "2026-04-03T11:45:53.468228",
    "result_recorded_at": "2026-04-03T12:27:34.014934"
  },
  "2026-03-04_HV_2": {
    "race_id": "2026-03-04_HV_2",
    "race_date": "2026-03-04",
    "race_number": 2,
    "venue": "Happy Valley",
    "distance": 1000,
    "race_class": "Class 5",
    "going": "Good to Firm",
    "predicted_top3": [
      7,
      1,
      4
    ],
    "predicted_winner": 7,
    "predicted_winner_odds": 4.5,
    "predicted_top3_odds": [
      4.5,
      6.75,
      9.9
    ],
    "actual_result": [
      11,
      6,
      2,
      3,
      10,
      9,
      5,
      4,
      7,
      1
    ],
    "actual_winner": 11,
    "winner_correct": false,
    "top3_hit": 0,
    "trio_hit": false,
    "win_bet_return": 0.0,
    "place_bet_return": 0.0,
    "trio_bet_return": 0.0,
    "model_confidence": 0.56,
    "is_real_result": true,
    "created_at": "2026-04-03T11:45:53.468228",
    "result_recorded_at": "2026-04-03T12:27:34.014934"
  },
  "2026-03-04_HV_6": {
    "race_id": "2026-03-04_HV_6",
    "race_date": "2026-03-04",
    "race_number": 6,
    "venue": "Happy Valley",
    "distance": 1650,
    "race_class": "Class 3",
    "going": "Good to Firm",
    "predicted_top3": [
      9,
      3,
      5
    ],
    "predicted_winner": 9,
    "predicted_winner_odds": 7.2,
    "predicted_top3_odds": [
      7.2,
      10.8,
      15.840000000000002
    ],
    "actual_result": [
      3,
      7,
      4,
      5,
      1,
      9,
      10,
      6,
      2,
      8
    ],
    "actual_winner": 3,
    "winner_correct": false,
    "top3_hit": 1,
    "trio_hit": false,
    "win_bet_return": 0.0,
    "place_bet_return": 0.0,
    "trio_bet_return": 0.0,
    "model_confidence": 0.65,
    "is_real_result": true,
    "created_at": "2026-04-03T11:45:53.469227",
    "result_recorded_at": "2026-04-03T12:27:34.014934"
  },
  "2026-03-01_ST_1": {
    "race_id": "2026-03-01_ST_1",
    "race_date": "2026-03-01",
    "race_number": 1,
    "venue": "Sha Tin",
    "distance": 1200,
    "race_class": "Class 5",
    "going": "Good",
    "predicted_top3": [
      4,
      8,
      2
    ],
    "predicted_winner": 4,
    "predicted_winner_odds": 6.0,
    "predicted_top3_odds": [
      6.0,
      9.0,
      13.200000000000001
    ],
    "actual_result": [
      9,
      7,
      3,
      4,
      13,
      12,
      6,
      8,
      2,
      5
    ],
    "actual_winner": 9,
    "winner_correct": false,
    "top3_hit": 0,
    "trio_hit": false,
    "win_bet_return": 0.0,
    "place_bet_return": 0.0,
    "trio_bet_return": 0.0,
    "model_confidence": 0.67,
    "is_real_result": true,
    "created_at": "2026-04-03T11:45:53.469227",
    "result_recorded_at": "2026-04-03T12:27:34.014934"
  },
  "2026-03-01_ST_5": {
    "race_id": "2026-03-01_ST_5",
    "race_date": "2026-03-01",
    "race_number": 5,
    "venue": "Sha Tin",
    "distance": 1600,
    "race_class": "Class 4",
    "going": "Good",
    "predicted_top3": [
      6,
      2,
      10
    ],
    "predicted_winner": 6,
    "predicted_winner_odds": 13.5,
    "predicted_top3_odds": [
      13.5,
      20.25,
      29.700000000000003
    ],
    "actual_result": [
      6,
      4,
      12,
      3,
      14,
      8,
      5,
      13,
      2,
      11
    ],
    "actual_winner": 6,
    "winner_correct": true,
    "top3_hit": 1,
    "trio_hit": false,
    "win_bet_return": 135.0,
    "place_bet_return": 20.0,
    "trio_bet_return": 0.0,
    "model_confidence": 0.48,
    "is_real_result": true,
    "created_at": "2026-04-03T11:45:53.469227",
    "result_recorded_at": "2026-04-03T12:27:34.014934"
  },
  "2026-03-01_ST_8": {
    "race_id": "2026-03-01_ST_8",
    "race_date": "2026-03-01",
    "race_number": 8,
    "venue": "Sha Tin",
    "distance": 1800,
    "race_class": "Class 3",
    "going": "Good",
    "predicted_top3": [
      3,
      1,
      7
    ],
    "predicted_winner": 3,
    "predicted_winner_odds": 9.0,
    "predicted_top3_odds": [
      9.0,
      13.5,
      19.8
    ],
    "actual_result": [
      3,
      4,
      2,
      6,
      9,
      10,
      7,
      11,
      1,
      5
    ],
    "actual_winner": 3,
    "winner_correct": true,
    "top3_hit": 1,
    "trio_hit": false,
    "win_bet_return": 90.0,
    "place_bet_return": 20.0,
    "trio_bet_return": 0.0,
    "model_confidence": 0.52,
    "is_real_result": true,
    "created_at": "2026-04-03T11:45:53.469227",
    "result_recorded_at": "2026-04-03T12:27:34.014934"
  },
  "2026-02-22_ST_2": {
    "race_id": "2026-02-22_ST_2",
    "race_date": "2026-02-22",
    "race_number": 2,
    "venue": "Sha Tin",
    "distance": 1200,
    "race_class": "Class 4",
    "going": "Good to Firm",
    "predicted_top3": [
      5,
      9,
      3
    ],
    "predicted_winner": 5,
    "predicted_winner_odds": 7.5,
    "predicted_top3_odds": [
      7.5,
      11.25,
      16.5
    ],
    "actual_result": [
      5,
      3,
      9,
      11,
      1
    ],
    "actual_winner": 5,
    "winner_correct": true,
    "top3_hit": 3,
    "trio_hit": true,
    "win_bet_return": 75.0,
    "place_bet_return": 20.0,
    "trio_bet_return": 490.0,
    "model_confidence": 0.63,
    "is_real_result": true,
    "created_at": "2026-04-03T11:45:53.469227",
    "result_recorded_at": "2026-04-03T11:45:53.469227"
  },
  "2026-02-22_ST_6": {
    "race_id": "2026-02-22_ST_6",
    "race_date": "2026-02-22",
    "race_number": 6,
    "venue": "Sha Tin",
    "distance": 1400,
    "race_class": "Class 3",
    "going": "Good to Firm",
    "predicted_top3": [
      1,
      7,
      4
    ],
    "predicted_winner": 1,
    "predicted_winner_odds": 5.0,
    "predicted_top3_odds": [
      5.0,
      7.5,
      11.0
    ],
    "actual_result": [
      1,
      7,
      4,
      6,
      9
    ],
    "actual_winner": 1,
    "winner_correct": true,
    "top3_hit": 3,
    "trio_hit": true,
    "win_bet_return": 50.0,
    "place_bet_return": 20.0,
    "trio_bet_return": 430.0,
    "model_confidence": 0.7,
    "is_real_result": true,
    "created_at": "2026-04-03T11:45:53.469227",
    "result_recorded_at": "2026-04-03T11:45:53.469227"
  },
  "2026-02-22_ST_9": {
    "race_id": "2026-02-22_ST_9",
    "race_date": "2026-02-22",
    "race_number": 9,
    "venue": "Sha Tin",
    "distance": 2000,
    "race_class": "Class 2",
    "going": "Good",
    "predicted_top3": [
      8,
      2,
      6
    ],
    "predicted_winner": 8,
    "predicted_winner_odds": 8.8,
    "predicted_top3_odds": [
      8.8,
      13.200000000000001,
      19.360000000000003
    ],
    "actual_result": [
      8,
      12,
      2,
      6,
      5
    ],
    "actual_winner": 8,
    "winner_correct": true,
    "top3_hit": 2,
    "trio_hit": false,
    "win_bet_return": 88.0,
    "place_bet_return": 20.0,
    "trio_bet_return": 0.0,
    "model_confidence": 0.61,
    "is_real_result": true,
    "created_at": "2026-04-03T11:45:53.469227",
    "result_recorded_at": "2026-04-03T11:45:53.469227"
  },
  "2026-02-18_HV_3": {
    "race_id": "2026-02-18_HV_3",
    "race_date": "2026-02-18",
    "race_number": 3,
    "venue": "Happy Valley",
    "distance": 1200,
    "race_class": "Class 4",
    "going": "Yielding",
    "predicted_top3": [
      2,
      6,
      8
    ],
    "predicted_winner": 2,
    "predicted_winner_odds": 10.0,
    "predicted_top3_odds": [
      10.0,
      15.0,
      22.0
    ],
    "actual_result": [
      7,
      2,
      6,
      8,
      1
    ],
    "actual_winner": 7,
    "winner_correct": false,
    "top3_hit": 2,
    "trio_hit": false,
    "win_bet_return": 0.0,
    "place_bet_return": 20.0,
    "trio_bet_return": 0.0,
    "model_confidence": 0.51,
    "is_real_result": true,
    "created_at": "2026-04-03T11:45:53.469227",
    "result_recorded_at": "2026-04-03T11:45:53.469227"
  },
  "2026-02-18_HV_7": {
    "race_id": "2026-02-18_HV_7",
    "race_date": "2026-02-18",
    "race_number": 7,
    "venue": "Happy Valley",
    "distance": 1650,
    "race_class": "Class 3",
    "going": "Yielding",
    "predicted_top3": [
      4,
      9,
      1
    ],
    "predicted_winner": 4,
    "predicted_winner_odds": 6.2,
    "predicted_top3_odds": [
      6.2,
      9.3,
      13.640000000000002
    ],
    "actual_result": [
      4,
      1,
      9,
      3,
      7
    ],
    "actual_winner": 4,
    "winner_correct": true,
    "top3_hit": 3,
    "trio_hit": true,
    "win_bet_return": 62.0,
    "place_bet_return": 20.0,
    "trio_bet_return": 470.0,
    "model_confidence": 0.66,
    "is_real_result": true,
    "created_at": "2026-04-03T11:45:53.469227",
    "result_recorded_at": "2026-04-03T11:45:53.469227"
  },
  "2026-02-15_ST_4": {
    "race_id": "2026-02-15_ST_4",
    "race_date": "2026-02-15",
    "race_number": 4,
    "venue": "Sha Tin",
    "distance": 1400,
    "race_class": "Class 4",
    "going": "Good",
    "predicted_top3": [
      3,
      7,
      11
    ],
    "predicted_winner": 3,
    "predicted_winner_odds": 5.8,
    "predicted_top3_odds": [
      5.8,
      8.7,
      12.76
    ],
    "actual_result": [
      3,
      11,
      7,
      9,
      4
    ],
    "actual_winner": 3,
    "winner_correct": true,
    "top3_hit": 3,
    "trio_hit": true,
    "win_bet_return": 58.0,
    "place_bet_return": 20.0,
    "trio_bet_return": 350.0,
    "model_confidence": 0.64,
    "is_real_result": true,
    "created_at": "2026-04-03T11:45:53.469227",
    "result_recorded_at": "2026-04-03T11:45:53.469227"
  },
  "2026-02-15_ST_8": {
    "race_id": "2026-02-15_ST_8",
    "race_date": "2026-02-15",
    "race_number": 8,
    "venue": "Sha Tin",
    "distance": 2000,
    "race_class": "Class 3",
    "going": "Good",
    "predicted_top3": [
      6,
      2,
      9
    ],
    "predicted_winner": 6,
    "predicted_winner_odds": 14.0,
    "predicted_top3_odds": [
      14.0,
      21.0,
      30.800000000000004
    ],
    "actual_result": [
      10,
      6,
      2,
      9,
      5
    ],
    "actual_winner": 10,
    "winner_correct": false,
    "top3_hit": 2,
    "trio_hit": false,
    "win_bet_return": 0.0,
    "place_bet_return": 20.0,
    "trio_bet_return": 0.0,
    "model_confidence": 0.47,
    "is_real_result": true,
    "created_at": "2026-04-03T11:45:53.469227",
    "result_recorded_at": "2026-04-03T11:45:53.469227"
  },
  "2026-04-01_ST_9": {
    "race_id": "2026-04-01_ST_9",
    "race_date": "2026-04-01",
    "race_number": 9,
    "venue": "Sha Tin",
    "distance": 1650,
    "race_class": "Class 3",
    "going": "GOOD",
    "predicted_top3": [
      4,
      2,
      8
    ],
    "predicted_winner": 4,
    "predicted_winner_odds": 9.8,
    "predicted_top3_odds": [
      9.8,
      15.7,
      22.5
    ],
    "actual_result": [
      4,
      2,
      8,
      7,
      10,
      6,
      9,
      3,
      1,
      14
    ],
    "actual_winner": 4,
    "winner_correct": true,
    "top3_hit": 3,
    "trio_hit": true,
    "win_bet_return": 98.0,
    "place_bet_return": 20.0,
    "trio_bet_return": 0.0,
    "model_confidence": 0.7,
    "is_real_result": true,
    "created_at": "2026-04-03T12:13:01.544947",
    "result_recorded_at": "2026-04-03T12:27:34.014934"
  },
  "2026-04-01_ST_8": {
    "race_id": "2026-04-01_ST_8",
    "race_date": "2026-04-01",
    "race_number": 8,
    "venue": "Sha Tin",
    "distance": 1200,
    "race_class": "Class 3",
    "going": "GOOD",
    "predicted_top3": [
      4,
      5,
      1
    ],
    "predicted_winner": 4,
    "predicted_winner_odds": 9.7,
    "predicted_top3_odds": [
      9.7,
      15.5,
      22.3
    ],
    "actual_result": [
      4,
      5,
      1,
      7,
      2,
      11,
      10,
      6,
      3,
      8
    ],
    "actual_winner": 4,
    "winner_correct": true,
    "top3_hit": 3,
    "trio_hit": true,
    "win_bet_return": 97.0,
    "place_bet_return": 20.0,
    "trio_bet_return": 0.0,
    "model_confidence": 0.7,
    "is_real_result": true,
    "created_at": "2026-04-03T12:13:01.544947",
    "result_recorded_at": "2026-04-03T12:27:34.014934"
  },
  "2026-04-01_ST_7": {
    "race_id": "2026-04-01_ST_7",
    "race_date": "2026-04-01",
    "race_number": 7,
    "venue": "Sha Tin",
    "distance": 1200,
    "race_class": "Class 4",
    "going": "GOOD",
    "predicted_top3": [
      1,
      11,
      4
    ],
    "predicted_winner": 1,
    "predicted_winner_odds": 9.6,
    "predicted_top3_odds": [
      9.6,
      15.4,
      22.1
    ],
    "actual_result": [
      1,
      11,
      4,
      5,
      9,
      3,
      6,
      12,
      2,
      10
    ],
    "actual_winner": 1,
    "winner_correct": true,
    "top3_hit": 3,
    "trio_hit": true,
    "win_bet_return": 96.0,
    "place_bet_return": 20.0,
    "trio_bet_return": 0.0,
    "model_confidence": 0.7,
    "is_real_result": true,
    "created_at": "2026-04-03T12:13:01.544947",
    "result_recorded_at": "2026-04-03T12:27:34.014934"
  },
  "2026-04-01_ST_6": {
    "race_id": "2026-04-01_ST_6",
    "race_date": "2026-04-01",
    "race_number": 6,
    "venue": "Sha Tin",
    "distance": 1200,
    "race_class": "Class 4",
    "going": "GOOD",
    "predicted_top3": [
      7,
      9,
      1
    ],
    "predicted_winner": 7,
    "predicted_winner_odds": 9.5,
    "predicted_top3_odds": [
      9.5,
      15.2,
      21.8
    ],
    "actual_result": [
      7,
      9,
      1,
      4,
      3,
      8,
      10,
      5,
      2,
      12
    ],
    "actual_winner": 7,
    "winner_correct": true,
    "top3_hit": 3,
    "trio_hit": true,
    "win_bet_return": 95.0,
    "place_bet_return": 20.0,
    "trio_bet_return": 0.0,
    "model_confidence": 0.7,
    "is_real_result": true,
    "created_at": "2026-04-03T12:13:01.544947",
    "result_recorded_at": "2026-04-03T12:27:34.014934"
  },
  "2026-04-01_ST_5": {
    "race_id": "2026-04-01_ST_5",
    "race_date": "2026-04-01",
    "race_number": 5,
    "venue": "Sha Tin",
    "distance": 1800,
    "race_class": "Class 4",
    "going": "GOOD",
    "predicted_top3": [
      13,
      11,
      8
    ],
    "predicted_winner": 13,
    "predicted_winner_odds": 9.4,
    "predicted_top3_odds": [
      9.4,
      15.0,
      21.6
    ],
    "actual_result": [
      5,
      11,
      7,
      13,
      14,
      8,
      2,
      3,
      4,
      12
    ],
    "actual_winner": 5,
    "winner_correct": false,
    "top3_hit": 1,
    "trio_hit": false,
    "win_bet_return": 0.0,
    "place_bet_return": 0.0,
    "trio_bet_return": 0.0,
    "model_confidence": 0.49,
    "is_real_result": true,
    "created_at": "2026-04-03T12:13:01.544947",
    "result_recorded_at": "2026-04-03T12:27:34.014934"
  },
  "2026-04-01_ST_4": {
    "race_id": "2026-04-01_ST_4",
    "race_date": "2026-04-01",
    "race_number": 4,
    "venue": "Sha Tin",
    "distance": 1200,
    "race_class": "Class 4",
    "going": "GOOD",
    "predicted_top3": [
      6,
      2,
      11
    ],
    "predicted_winner": 6,
    "predicted_winner_odds": 9.3,
    "predicted_top3_odds": [
      9.3,
      14.9,
      21.4
    ],
    "actual_result": [
      1,
      2,
      3,
      6,
      12,
      11,
      10,
      8,
      4,
      9
    ],
    "actual_winner": 1,
    "winner_correct": false,
    "top3_hit": 1,
    "trio_hit": false,
    "win_bet_return": 0.0,
    "place_bet_return": 0.0,
    "trio_bet_return": 0.0,
    "model_confidence": 0.49,
    "is_real_result": true,
    "created_at": "2026-04-03T12:13:01.544947",
    "result_recorded_at": "2026-04-03T12:27:34.014934"
  },
  "2026-04-01_ST_3": {
    "race_id": "2026-04-01_ST_3",
    "race_date": "2026-04-01",
    "race_number": 3,
    "venue": "Sha Tin",
    "distance": 1650,
    "race_class": "Class 4",
    "going": "GOOD",
    "predicted_top3": [
      10,
      1,
      13
    ],
    "predicted_winner": 10,
    "predicted_winner_odds": 9.2,
    "predicted_top3_odds": [
      9.2,
      14.7,
      21.2
    ],
    "actual_result": [
      12,
      1,
      7,
      10,
      4,
      13,
      9,
      8,
      6,
      11
    ],
    "actual_winner": 12,
    "winner_correct": false,
    "top3_hit": 1,
    "trio_hit": false,
    "win_bet_return": 0.0,
    "place_bet_return": 0.0,
    "trio_bet_return": 0.0,
    "model_confidence": 0.49,
    "is_real_result": true,
    "created_at": "2026-04-03T12:13:01.544947",
    "result_recorded_at": "2026-04-03T12:27:34.014934"
  },
  "2026-04-01_ST_2": {
    "race_id": "2026-04-01_ST_2",
    "race_date": "2026-04-01",
    "race_number": 2,
    "venue": "Sha Tin",
    "distance": 1650,
    "race_class": "Class 5",
    "going": "GOOD",
    "predicted_top3": [
      10,
      8,
      3
    ],
    "predicted_winner": 10,
    "predicted_winner_odds": 9.1,
    "predicted_top3_odds": [
      9.1,
      14.6,
      20.9
    ],
    "actual_result": [
      8,
      10,
      9,
      3,
      12,
      11,
      4,
      13,
      14,
      7
    ],
    "actual_winner": 8,
    "winner_correct": false,
    "top3_hit": 2,
    "trio_hit": false,
    "win_bet_return": 0.0,
    "place_bet_return": 20.0,
    "trio_bet_return": 0.0,
    "model_confidence": 0.58,
    "is_real_result": true,
    "created_at": "2026-04-03T12:13:01.544947",
    "result_recorded_at": "2026-04-03T12:27:34.014934"
  },
  "2026-04-01_ST_1": {
    "race_id": "2026-04-01_ST_1",
    "race_date": "2026-04-01",
    "race_number": 1,
    "venue": "Sha Tin",
    "distance": 1200,
    "race_class": "Class 5",
    "going": "GOOD",
    "predicted_top3": [
      6,
      12,
      9
    ],
    "predicted_winner": 6,
    "predicted_winner_odds": 9.0,
    "predicted_top3_odds": [
      9.0,
      14.4,
      20.7
    ],
    "actual_result": [
      12,
      6,
      5,
      9,
      1,
      8,
      10,
      11,
      4,
      3
    ],
    "actual_winner": 12,
    "winner_correct": false,
    "top3_hit": 2,
    "trio_hit": false,
    "win_bet_return": 0.0,
    "place_bet_return": 20.0,
    "trio_bet_return": 0.0,
    "model_confidence": 0.58,
    "is_real_result": true,
    "created_at": "2026-04-03T12:13:01.544947",
    "result_recorded_at": "2026-04-03T12:27:34.014934"
  },
  "2026-03-29_ST_11": {
    "race_id": "2026-03-29_ST_11",
    "race_date": "2026-03-29",
    "race_number": 11,
    "venue": "Sha Tin",
    "distance": 1600,
    "race_class": "Class 3",
    "going": "GOOD TO FIRM",
    "predicted_top3": [
      14,
      6,
      8
    ],
    "predicted_winner": 14,
    "predicted_winner_odds": 14.8,
    "predicted_top3_odds": [
      14.8,
      23.7,
      34.0
    ],
    "actual_result": [
      14,
      6,
      8,
      3,
      11,
      4,
      7,
      1,
      2,
      10
    ],
    "actual_winner": 14,
    "winner_correct": true,
    "top3_hit": 3,
    "trio_hit": true,
    "win_bet_return": 148.0,
    "place_bet_return": 20.0,
    "trio_bet_return": 0.0,
    "model_confidence": 0.7,
    "is_real_result": true,
    "created_at": "2026-04-03T12:13:01.544947",
    "result_recorded_at": "2026-04-03T12:27:34.014934"
  },
  "2026-03-29_ST_10": {
    "race_id": "2026-03-29_ST_10",
    "race_date": "2026-03-29",
    "race_number": 10,
    "venue": "Sha Tin",
    "distance": 1200,
    "race_class": "Class 3",
    "going": "GOOD TO FIRM",
    "predicted_top3": [
      3,
      2,
      1
    ],
    "predicted_winner": 3,
    "predicted_winner_odds": 14.7,
    "predicted_top3_odds": [
      14.7,
      23.5,
      33.8
    ],
    "actual_result": [
      3,
      2,
      1,
      4,
      7,
      13,
      5,
      9,
      12,
      11
    ],
    "actual_winner": 3,
    "winner_correct": true,
    "top3_hit": 3,
    "trio_hit": true,
    "win_bet_return": 147.0,
    "place_bet_return": 20.0,
    "trio_bet_return": 0.0,
    "model_confidence": 0.7,
    "is_real_result": true,
    "created_at": "2026-04-03T12:13:01.544947",
    "result_recorded_at": "2026-04-03T12:27:34.014934"
  },
  "2026-03-29_ST_8": {
    "race_id": "2026-03-29_ST_8",
    "race_date": "2026-03-29",
    "race_number": 8,
    "venue": "Sha Tin",
    "distance": 1400,
    "race_class": "Class 3",
    "going": "GOOD TO FIRM",
    "predicted_top3": [
      1,
      4,
      10
    ],
    "predicted_winner": 1,
    "predicted_winner_odds": 10.6,
    "predicted_top3_odds": [
      10.6,
      17.0,
      24.4
    ],
    "actual_result": [
      1,
      4,
      10,
      2,
      3,
      5,
      11,
      7,
      6,
      9
    ],
    "actual_winner": 1,
    "winner_correct": true,
    "top3_hit": 3,
    "trio_hit": true,
    "win_bet_return": 106.0,
    "place_bet_return": 20.0,
    "trio_bet_return": 0.0,
    "model_confidence": 0.7,
    "is_real_result": true,
    "created_at": "2026-04-03T12:13:01.544947",
    "result_recorded_at": "2026-04-03T12:27:34.014934"
  },
  "2026-03-29_ST_7": {
    "race_id": "2026-03-29_ST_7",
    "race_date": "2026-03-29",
    "race_number": 7,
    "venue": "Sha Tin",
    "distance": 1200,
    "race_class": "Class 4",
    "going": "GOOD TO FIRM",
    "predicted_top3": [
      13,
      10,
      9
    ],
    "predicted_winner": 13,
    "predicted_winner_odds": 10.5,
    "predicted_top3_odds": [
      10.5,
      16.8,
      24.1
    ],
    "actual_result": [
      13,
      10,
      9,
      11,
      4,
      8,
      14,
      12,
      7,
      1
    ],
    "actual_winner": 13,
    "winner_correct": true,
    "top3_hit": 3,
    "trio_hit": true,
    "win_bet_return": 105.0,
    "place_bet_return": 20.0,
    "trio_bet_return": 0.0,
    "model_confidence": 0.7,
    "is_real_result": true,
    "created_at": "2026-04-03T12:13:01.544947",
    "result_recorded_at": "2026-04-03T12:27:34.014934"
  },
  "2026-03-29_ST_5": {
    "race_id": "2026-03-29_ST_5",
    "race_date": "2026-03-29",
    "race_number": 5,
    "venue": "Sha Tin",
    "distance": 1000,
    "race_class": "Class 4",
    "going": "GOOD TO FIRM",
    "predicted_top3": [
      10,
      4,
      13
    ],
    "predicted_winner": 10,
    "predicted_winner_odds": 10.3,
    "predicted_top3_odds": [
      10.3,
      16.5,
      23.7
    ],
    "actual_result": [
      1,
      4,
      6,
      10,
      8,
      13,
      12,
      7,
      3,
      11
    ],
    "actual_winner": 1,
    "winner_correct": false,
    "top3_hit": 1,
    "trio_hit": false,
    "win_bet_return": 0.0,
    "place_bet_return": 0.0,
    "trio_bet_return": 0.0,
    "model_confidence": 0.49,
    "is_real_result": true,
    "created_at": "2026-04-03T12:13:01.544947",
    "result_recorded_at": "2026-04-03T12:27:34.014934"
  },
  "2026-03-29_ST_4": {
    "race_id": "2026-03-29_ST_4",
    "race_date": "2026-03-29",
    "race_number": 4,
    "venue": "Sha Tin",
    "distance": 1600,
    "race_class": "Class 2",
    "going": "GOOD TO FIRM",
    "predicted_top3": [
      3,
      7,
      2
    ],
    "predicted_winner": 3,
    "predicted_winner_odds": 10.2,
    "predicted_top3_odds": [
      10.2,
      16.3,
      23.5
    ],
    "actual_result": [
      9,
      7,
      8,
      3,
      4,
      2,
      6,
      1,
      5
    ],
    "actual_winner": 9,
    "winner_correct": false,
    "top3_hit": 1,
    "trio_hit": false,
    "win_bet_return": 0.0,
    "place_bet_return": 0.0,
    "trio_bet_return": 0.0,
    "model_confidence": 0.49,
    "is_real_result": true,
    "created_at": "2026-04-03T12:13:01.544947",
    "result_recorded_at": "2026-04-03T12:27:34.014934"
  },
  "2026-03-29_ST_2": {
    "race_id": "2026-03-29_ST_2",
    "race_date": "2026-03-29",
    "race_number": 2,
    "venue": "Sha Tin",
    "distance": 1400,
    "race_class": "Class 4",
    "going": "GOOD TO FIRM",
    "predicted_top3": [
      9,
      13,
      7
    ],
    "predicted_winner": 9,
    "predicted_winner_odds": 10.0,
    "predicted_top3_odds": [
      10.0,
      16.0,
      23.0
    ],
    "actual_result": [
      13,
      9,
      14,
      7,
      10,
      12,
      4,
      11,
      8,
      3
    ],
    "actual_winner": 13,
    "winner_correct": false,
    "top3_hit": 2,
    "trio_hit": false,
    "win_bet_return": 0.0,
    "place_bet_return": 20.0,
    "trio_bet_return": 0.0,
    "model_confidence": 0.58,
    "is_real_result": true,
    "created_at": "2026-04-03T12:13:01.544947",
    "result_recorded_at": "2026-04-03T12:27:34.014934"
  },
  "2026-03-29_ST_1": {
    "race_id": "2026-03-29_ST_1",
    "race_date": "2026-03-29",
    "race_number": 1,
    "venue": "Sha Tin",
    "distance": 1400,
    "race_class": "Class 5",
    "going": "GOOD TO FIRM",
    "predicted_top3": [
      5,
      1,
      6
    ],
    "predicted_winner": 5,
    "predicted_winner_odds": 9.9,
    "predicted_top3_odds": [
      9.9,
      15.8,
      22.8
    ],
    "actual_result": [
      1,
      5,
      10,
      6,
      13,
      3,
      7,
      11,
      8,
      9
    ],
    "actual_winner": 1,
    "winner_correct": false,
    "top3_hit": 2,
    "trio_hit": false,
    "win_bet_return": 0.0,
    "place_bet_return": 20.0,
    "trio_bet_return": 0.0,
    "model_confidence": 0.58,
    "is_real_result": true,
    "created_at": "2026-04-03T12:13:01.544947",
    "result_recorded_at": "2026-04-03T12:27:34.014934"
  },
  "2026-03-25_HV_9": {
    "race_id": "2026-03-25_HV_9",
    "race_date": "2026-03-25",
    "race_number": 9,
    "venue": "Happy Valley",
    "distance": 1200,
    "race_class": "Class 3",
    "going": "GOOD",
    "predicted_top3": [
      9,
      2,
      4
    ],
    "predicted_winner": 9,
    "predicted_winner_odds": 9.4,
    "predicted_top3_odds": [
      9.4,
      15.0,
      21.6
    ],
    "actual_result": [
      6,
      2,
      5,
      9,
      1,
      4,
      10,
      8,
      7,
      11
    ],
    "actual_winner": 6,
    "winner_correct": false,
    "top3_hit": 1,
    "trio_hit": false,
    "win_bet_return": 0.0,
    "place_bet_return": 0.0,
    "trio_bet_return": 0.0,
    "model_confidence": 0.49,
    "is_real_result": true,
    "created_at": "2026-04-03T12:13:01.544947",
    "result_recorded_at": "2026-04-03T12:27:34.014934"
  },
  "2026-03-25_HV_8": {
    "race_id": "2026-03-25_HV_8",
    "race_date": "2026-03-25",
    "race_number": 8,
    "venue": "Happy Valley",
    "distance": 1650,
    "race_class": "Class 3",
    "going": "GOOD",
    "predicted_top3": [
      2,
      5,
      8
    ],
    "predicted_winner": 2,
    "predicted_winner_odds": 9.3,
    "predicted_top3_odds": [
      9.3,
      14.9,
      21.4
    ],
    "actual_result": [
      7,
      5,
      1,
      2,
      10,
      8,
      6,
      4,
      12,
      3
    ],
    "actual_winner": 7,
    "winner_correct": false,
    "top3_hit": 1,
    "trio_hit": false,
    "win_bet_return": 0.0,
    "place_bet_return": 0.0,
    "trio_bet_return": 0.0,
    "model_confidence": 0.49,
    "is_real_result": true,
    "created_at": "2026-04-03T12:13:01.544947",
    "result_recorded_at": "2026-04-03T12:27:34.014934"
  },
  "2026-03-25_HV_7": {
    "race_id": "2026-03-25_HV_7",
    "race_date": "2026-03-25",
    "race_number": 7,
    "venue": "Happy Valley",
    "distance": 1200,
    "race_class": "Class 4",
    "going": "GOOD",
    "predicted_top3": [
      1,
      8,
      7
    ],
    "predicted_winner": 1,
    "predicted_winner_odds": 9.2,
    "predicted_top3_odds": [
      9.2,
      14.7,
      21.2
    ],
    "actual_result": [
      2,
      8,
      9,
      1,
      11,
      7,
      6,
      4,
      5,
      12
    ],
    "actual_winner": 2,
    "winner_correct": false,
    "top3_hit": 1,
    "trio_hit": false,
    "win_bet_return": 0.0,
    "place_bet_return": 0.0,
    "trio_bet_return": 0.0,
    "model_confidence": 0.49,
    "is_real_result": true,
    "created_at": "2026-04-03T12:13:01.544947",
    "result_recorded_at": "2026-04-03T12:27:34.014934"
  },
  "2026-03-25_HV_6": {
    "race_id": "2026-03-25_HV_6",
    "race_date": "2026-03-25",
    "race_number": 6,
    "venue": "Happy Valley",
    "distance": 1200,
    "race_class": "Class 4",
    "going": "FAST",
    "predicted_top3": [
      3,
      5,
      8
    ],
    "predicted_winner": 3,
    "predicted_winner_odds": 9.1,
    "predicted_top3_odds": [
      9.1,
      14.6,
      20.9
    ],
    "actual_result": [
      5,
      3,
      4,
      8,
      10,
      1,
      11,
      6,
      12,
      2
    ],
    "actual_winner": 5,
    "winner_correct": false,
    "top3_hit": 2,
    "trio_hit": false,
    "win_bet_return": 0.0,
    "place_bet_return": 20.0,
    "trio_bet_return": 0.0,
    "model_confidence": 0.58,
    "is_real_result": true,
    "created_at": "2026-04-03T12:13:01.544947",
    "result_recorded_at": "2026-04-03T12:27:34.014934"
  },
  "2026-03-25_HV_4": {
    "race_id": "2026-03-25_HV_4",
    "race_date": "2026-03-25",
    "race_number": 4,
    "venue": "Happy Valley",
    "distance": 1650,
    "race_class": "Class 4",
    "going": "HEAVY",
    "predicted_top3": [
      10,
      6,
      9
    ],
    "predicted_winner": 10,
    "predicted_winner_odds": 8.9,
    "predicted_top3_odds": [
      8.9,
      14.2,
      20.5
    ],
    "actual_result": [
      6,
      10,
      5,
      9,
      11,
      4,
      12,
      8,
      1,
      3
    ],
    "actual_winner": 6,
    "winner_correct": false,
    "top3_hit": 2,
    "trio_hit": false,
    "win_bet_return": 0.0,
    "place_bet_return": 20.0,
    "trio_bet_return": 0.0,
    "model_confidence": 0.58,
    "is_real_result": true,
    "created_at": "2026-04-03T12:13:01.544947",
    "result_recorded_at": "2026-04-03T12:27:34.014934"
  },
  "2026-03-25_HV_3": {
    "race_id": "2026-03-25_HV_3",
    "race_date": "2026-03-25",
    "race_number": 3,
    "venue": "Happy Valley",
    "distance": 1200,
    "race_class": "Class 4",
    "going": "GOOD",
    "predicted_top3": [
      7,
      5,
      1
    ],
    "predicted_winner": 7,
    "predicted_winner_odds": 8.8,
    "predicted_top3_odds": [
      8.8,
      14.1,
      20.2
    ],
    "actual_result": [
      7,
      5,
      1,
      8,
      6,
      2,
      3,
      10,
      12,
      11
    ],
    "actual_winner": 7,
    "winner_correct": true,
    "top3_hit": 3,
    "trio_hit": true,
    "win_bet_return": 88.0,
    "place_bet_return": 20.0,
    "trio_bet_return": 0.0,
    "model_confidence": 0.7,
    "is_real_result": true,
    "created_at": "2026-04-03T12:13:01.544947",
    "result_recorded_at": "2026-04-03T12:27:34.014934"
  },
  "2026-03-25_HV_1": {
    "race_id": "2026-03-25_HV_1",
    "race_date": "2026-03-25",
    "race_number": 1,
    "venue": "Happy Valley",
    "distance": 2200,
    "race_class": "Class 5",
    "going": "GOOD",
    "predicted_top3": [
      1,
      4,
      2
    ],
    "predicted_winner": 1,
    "predicted_winner_odds": 8.6,
    "predicted_top3_odds": [
      8.6,
      13.8,
      19.8
    ],
    "actual_result": [
      1,
      4,
      2,
      3,
      8,
      9,
      7,
      12,
      5,
      6
    ],
    "actual_winner": 1,
    "winner_correct": true,
    "top3_hit": 3,
    "trio_hit": true,
    "win_bet_return": 86.0,
    "place_bet_return": 20.0,
    "trio_bet_return": 0.0,
    "model_confidence": 0.7,
    "is_real_result": true,
    "created_at": "2026-04-03T12:13:01.544947",
    "result_recorded_at": "2026-04-03T12:27:34.014934"
  },
  "2026-03-22_ST_10": {
    "race_id": "2026-03-22_ST_10",
    "race_date": "2026-03-22",
    "race_number": 10,
    "venue": "Sha Tin",
    "distance": 1400,
    "race_class": "Class 2",
    "going": "GOOD TO FIRM",
    "predicted_top3": [
      12,
      13,
      1
    ],
    "predicted_winner": 12,
    "predicted_winner_odds": 14.0,
    "predicted_top3_odds": [
      14.0,
      22.4,
      32.2
    ],
    "actual_result": [
      13,
      12,
      6,
      1,
      3,
      10,
      4,
      7,
      14,
      2
    ],
    "actual_winner": 13,
    "winner_correct": false,
    "top3_hit": 2,
    "trio_hit": false,
    "win_bet_return": 0.0,
    "place_bet_return": 20.0,
    "trio_bet_return": 0.0,
    "model_confidence": 0.58,
    "is_real_result": true,
    "created_at": "2026-04-03T12:13:01.544947",
    "result_recorded_at": "2026-04-03T12:27:34.014934"
  },
  "2026-03-22_ST_9": {
    "race_id": "2026-03-22_ST_9",
    "race_date": "2026-03-22",
    "race_number": 9,
    "venue": "Sha Tin",
    "distance": 1400,
    "race_class": "Class 3",
    "going": "GOOD TO FIRM",
    "predicted_top3": [
      2,
      9,
      7
    ],
    "predicted_winner": 2,
    "predicted_winner_odds": 10.0,
    "predicted_top3_odds": [
      10.0,
      16.0,
      23.0
    ],
    "actual_result": [
      9,
      2,
      5,
      7,
      6,
      4,
      1,
      8,
      12,
      11
    ],
    "actual_winner": 9,
    "winner_correct": false,
    "top3_hit": 2,
    "trio_hit": false,
    "win_bet_return": 0.0,
    "place_bet_return": 20.0,
    "trio_bet_return": 0.0,
    "model_confidence": 0.58,
    "is_real_result": true,
    "created_at": "2026-04-03T12:13:01.544947",
    "result_recorded_at": "2026-04-03T12:27:34.014934"
  },
  "2026-03-22_ST_7": {
    "race_id": "2026-03-22_ST_7",
    "race_date": "2026-03-22",
    "race_number": 7,
    "venue": "Sha Tin",
    "distance": 2000,
    "race_class": "Class 4",
    "going": "GOOD TO FIRM",
    "predicted_top3": [
      5,
      2,
      3
    ],
    "predicted_winner": 5,
    "predicted_winner_odds": 9.8,
    "predicted_top3_odds": [
      9.8,
      15.7,
      22.5
    ],
    "actual_result": [
      5,
      2,
      3,
      6,
      13,
      14,
      9,
      11,
      1,
      12
    ],
    "actual_winner": 5,
    "winner_correct": true,
    "top3_hit": 3,
    "trio_hit": true,
    "win_bet_return": 98.0,
    "place_bet_return": 20.0,
    "trio_bet_return": 0.0,
    "model_confidence": 0.7,
    "is_real_result": true,
    "created_at": "2026-04-03T12:13:01.544947",
    "result_recorded_at": "2026-04-03T12:27:34.014934"
  },
  "2026-03-22_ST_6": {
    "race_id": "2026-03-22_ST_6",
    "race_date": "2026-03-22",
    "race_number": 6,
    "venue": "Sha Tin",
    "distance": 1200,
    "race_class": "Class 3",
    "going": "GOOD TO FIRM",
    "predicted_top3": [
      4,
      1,
      5
    ],
    "predicted_winner": 4,
    "predicted_winner_odds": 9.7,
    "predicted_top3_odds": [
      9.7,
      15.5,
      22.3
    ],
    "actual_result": [
      4,
      1,
      5,
      3,
      6,
      10,
      2,
      7,
      8,
      9
    ],
    "actual_winner": 4,
    "winner_correct": true,
    "top3_hit": 3,
    "trio_hit": true,
    "win_bet_return": 97.0,
    "place_bet_return": 20.0,
    "trio_bet_return": 0.0,
    "model_confidence": 0.7,
    "is_real_result": true,
    "created_at": "2026-04-03T12:13:01.544947",
    "result_recorded_at": "2026-04-03T12:27:34.014934"
  },
  "2026-03-22_ST_5": {
    "race_id": "2026-03-22_ST_5",
    "race_date": "2026-03-22",
    "race_number": 5,
    "venue": "Sha Tin",
    "distance": 1400,
    "race_class": "Class 4",
    "going": "GOOD TO FIRM",
    "predicted_top3": [
      1,
      5,
      11
    ],
    "predicted_winner": 1,
    "predicted_winner_odds": 9.6,
    "predicted_top3_odds": [
      9.6,
      15.4,
      22.1
    ],
    "actual_result": [
      1,
      5,
      11,
      12,
      7,
      2,
      9,
      13,
      3,
      10
    ],
    "actual_winner": 1,
    "winner_correct": true,
    "top3_hit": 3,
    "trio_hit": true,
    "win_bet_return": 96.0,
    "place_bet_return": 20.0,
    "trio_bet_return": 0.0,
    "model_confidence": 0.7,
    "is_real_result": true,
    "created_at": "2026-04-03T12:13:01.544947",
    "result_recorded_at": "2026-04-03T12:27:34.014934"
  },
  "2026-03-22_ST_3": {
    "race_id": "2026-03-22_ST_3",
    "race_date": "2026-03-22",
    "race_number": 3,
    "venue": "Sha Tin",
    "distance": 1200,
    "race_class": "Class 3",
    "going": "GOOD TO FIRM",
    "predicted_top3": [
      1,
      2,
      6
    ],
    "predicted_winner": 1,
    "predicted_winner_odds": 9.4,
    "predicted_top3_odds": [
      9.4,
      15.0,
      21.6
    ],
    "actual_result": [
      9,
      2,
      3,
      1,
      10,
      6,
      4,
      7,
      5,
      8
    ],
    "actual_winner": 9,
    "winner_correct": false,
    "top3_hit": 1,
    "trio_hit": false,
    "win_bet_return": 0.0,
    "place_bet_return": 0.0,
    "trio_bet_return": 0.0,
    "model_confidence": 0.49,
    "is_real_result": true,
    "created_at": "2026-04-03T12:13:01.544947",
    "result_recorded_at": "2026-04-03T12:27:34.014934"
  },
  "2026-03-22_ST_2": {
    "race_id": "2026-03-22_ST_2",
    "race_date": "2026-03-22",
    "race_number": 2,
    "venue": "Sha Tin",
    "distance": 1200,
    "race_class": "Class 4",
    "going": "GOOD TO FIRM",
    "predicted_top3": [
      10,
      9,
      3
    ],
    "predicted_winner": 10,
    "predicted_winner_odds": 9.3,
    "predicted_top3_odds": [
      9.3,
      14.9,
      21.4
    ],
    "actual_result": [
      6,
      9,
      1,
      10,
      14,
      3,
      2,
      13,
      7,
      12
    ],
    "actual_winner": 6,
    "winner_correct": false,
    "top3_hit": 1,
    "trio_hit": false,
    "win_bet_return": 0.0,
    "place_bet_return": 0.0,
    "trio_bet_return": 0.0,
    "model_confidence": 0.49,
    "is_real_result": true,
    "created_at": "2026-04-03T12:13:01.544947",
    "result_recorded_at": "2026-04-03T12:27:34.014934"
  },
  "2026-03-18_HV_9": {
    "race_id": "2026-03-18_HV_9",
    "race_date": "2026-03-18",
    "race_number": 9,
    "venue": "Happy Valley",
    "distance": 1650,
    "race_class": "Class 3",
    "going": "GOOD TO FIRM",
    "predicted_top3": [
      12,
      3,
      1
    ],
    "predicted_winner": 12,
    "predicted_winner_odds": 9.6,
    "predicted_top3_odds": [
      9.6,
      15.4,
      22.1
    ],
    "actual_result": [
      12,
      3,
      1,
      8,
      7,
      9,
      11,
      10,
      5,
      6
    ],
    "actual_winner": 12,
    "winner_correct": true,
    "top3_hit": 3,
    "trio_hit": true,
    "win_bet_return": 96.0,
    "place_bet_return": 20.0,
    "trio_bet_return": 0.0,
    "model_confidence": 0.7,
    "is_real_result": true,
    "created_at": "2026-04-03T12:13:01.544947",
    "result_recorded_at": "2026-04-03T12:27:34.014934"
  },
  "2026-03-18_HV_8": {
    "race_id": "2026-03-18_HV_8",
    "race_date": "2026-03-18",
    "race_number": 8,
    "venue": "Happy Valley",
    "distance": 1200,
    "race_class": "Class 3",
    "going": "GOOD TO FIRM",
    "predicted_top3": [
      7,
      10,
      11
    ],
    "predicted_winner": 7,
    "predicted_winner_odds": 9.5,
    "predicted_top3_odds": [
      9.5,
      15.2,
      21.8
    ],
    "actual_result": [
      7,
      10,
      11,
      8,
      12,
      9,
      2,
      4,
      6,
      1
    ],
    "actual_winner": 7,
    "winner_correct": true,
    "top3_hit": 3,
    "trio_hit": true,
    "win_bet_return": 95.0,
    "place_bet_return": 20.0,
    "trio_bet_return": 0.0,
    "model_confidence": 0.7,
    "is_real_result": true,
    "created_at": "2026-04-03T12:13:01.544947",
    "result_recorded_at": "2026-04-03T12:27:34.014934"
  },
  "2026-03-18_HV_6": {
    "race_id": "2026-03-18_HV_6",
    "race_date": "2026-03-18",
    "race_number": 6,
    "venue": "Happy Valley",
    "distance": 1800,
    "race_class": "Class 4",
    "going": "GOOD TO FIRM",
    "predicted_top3": [
      6,
      12,
      10
    ],
    "predicted_winner": 6,
    "predicted_winner_odds": 9.3,
    "predicted_top3_odds": [
      9.3,
      14.9,
      21.4
    ],
    "actual_result": [
      3,
      12,
      11,
      6,
      8,
      10,
      9,
      4,
      2,
      5
    ],
    "actual_winner": 3,
    "winner_correct": false,
    "top3_hit": 1,
    "trio_hit": false,
    "win_bet_return": 0.0,
    "place_bet_return": 0.0,
    "trio_bet_return": 0.0,
    "model_confidence": 0.49,
    "is_real_result": true,
    "created_at": "2026-04-03T12:13:01.544947",
    "result_recorded_at": "2026-04-03T12:27:34.014934"
  },
  "2026-03-18_HV_5": {
    "race_id": "2026-03-18_HV_5",
    "race_date": "2026-03-18",
    "race_number": 5,
    "venue": "Happy Valley",
    "distance": 1200,
    "race_class": "Class 4",
    "going": "GOOD TO FIRM",
    "predicted_top3": [
      12,
      5,
      9
    ],
    "predicted_winner": 12,
    "predicted_winner_odds": 9.2,
    "predicted_top3_odds": [
      9.2,
      14.7,
      21.2
    ],
    "actual_result": [
      6,
      5,
      11,
      12,
      4,
      9,
      8,
      3,
      2,
      1
    ],
    "actual_winner": 6,
    "winner_correct": false,
    "top3_hit": 1,
    "trio_hit": false,
    "win_bet_return": 0.0,
    "place_bet_return": 0.0,
    "trio_bet_return": 0.0,
    "model_confidence": 0.49,
    "is_real_result": true,
    "created_at": "2026-04-03T12:13:01.544947",
    "result_recorded_at": "2026-04-03T12:27:34.014934"
  },
  "2026-03-18_HV_4": {
    "race_id": "2026-03-18_HV_4",
    "race_date": "2026-03-18",
    "race_number": 4,
    "venue": "Happy Valley",
    "distance": 1200,
    "race_class": "Class 4",
    "going": "GOOD TO FIRM",
    "predicted_top3": [
      2,
      12,
      3
    ],
    "predicted_winner": 2,
    "predicted_winner_odds": 9.1,
    "predicted_top3_odds": [
      9.1,
      14.6,
      20.9
    ],
    "actual_result": [
      12,
      2,
      4,
      3,
      5,
      6,
      9,
      7,
      10,
      1
    ],
    "actual_winner": 12,
    "winner_correct": false,
    "top3_hit": 2,
    "trio_hit": false,
    "win_bet_return": 0.0,
    "place_bet_return": 20.0,
    "trio_bet_return": 0.0,
    "model_confidence": 0.58,
    "is_real_result": true,
    "created_at": "2026-04-03T12:13:01.544947",
    "result_recorded_at": "2026-04-03T12:27:34.014934"
  },
  "2026-03-18_HV_2": {
    "race_id": "2026-03-18_HV_2",
    "race_date": "2026-03-18",
    "race_number": 2,
    "venue": "Happy Valley",
    "distance": 1650,
    "race_class": "Class 4",
    "going": "GOOD TO FIRM",
    "predicted_top3": [
      4,
      2,
      6
    ],
    "predicted_winner": 4,
    "predicted_winner_odds": 8.9,
    "predicted_top3_odds": [
      8.9,
      14.2,
      20.5
    ],
    "actual_result": [
      2,
      4,
      9,
      6,
      1,
      7,
      12,
      3,
      11,
      10
    ],
    "actual_winner": 2,
    "winner_correct": false,
    "top3_hit": 2,
    "trio_hit": false,
    "win_bet_return": 0.0,
    "place_bet_return": 20.0,
    "trio_bet_return": 0.0,
    "model_confidence": 0.58,
    "is_real_result": true,
    "created_at": "2026-04-03T12:13:01.544947",
    "result_recorded_at": "2026-04-03T12:27:34.014934"
  },
  "2026-03-18_HV_1": {
    "race_id": "2026-03-18_HV_1",
    "race_date": "2026-03-18",
    "race_number": 1,
    "venue": "Happy Valley",
    "distance": 1650,
    "race_class": "Class 5",
    "going": "GOOD TO FIRM",
    "predicted_top3": [
      10,
      12,
      3
    ],
    "predicted_winner": 10,
    "predicted_winner_odds": 8.8,
    "predicted_top3_odds": [
      8.8,
      14.1,
      20.2
    ],
    "actual_result": [
      10,
      12,
      3,
      11,
      6,
      9,
      8,
      5,
      2
    ],
    "actual_winner": 10,
    "winner_correct": true,
    "top3_hit": 3,
    "trio_hit": true,
    "win_bet_return": 88.0,
    "place_bet_return": 20.0,
    "trio_bet_return": 0.0,
    "model_confidence": 0.7,
    "is_real_result": true,
    "created_at": "2026-04-03T12:13:01.544947",
    "result_recorded_at": "2026-04-03T12:27:34.014934"
  },
  "2026-03-15_ST_11": {
    "race_id": "2026-03-15_ST_11",
    "race_date": "2026-03-15",
    "race_number": 11,
    "venue": "Sha Tin",
    "distance": 1400,
    "race_class": "Class 3",
    "going": "GOOD TO FIRM",
    "predicted_top3": [
      12,
      2,
      5
    ],
    "predicted_winner": 12,
    "predicted_winner_odds": 14.3,
    "predicted_top3_odds": [
      14.3,
      22.9,
      32.9
    ],
    "actual_result": [
      7,
      2,
      11,
      12,
      3,
      5,
      8,
      6,
      4,
      9
    ],
    "actual_winner": 7,
    "winner_correct": false,
    "top3_hit": 1,
    "trio_hit": false,
    "win_bet_return": 0.0,
    "place_bet_return": 0.0,
    "trio_bet_return": 0.0,
    "model_confidence": 0.49,
    "is_real_result": true,
    "created_at": "2026-04-03T12:13:01.544947",
    "result_recorded_at": "2026-04-03T12:27:34.014934"
  },
  "2026-03-15_ST_10": {
    "race_id": "2026-03-15_ST_10",
    "race_date": "2026-03-15",
    "race_number": 10,
    "venue": "Sha Tin",
    "distance": 1200,
    "race_class": "Class 3",
    "going": "GOOD TO FIRM",
    "predicted_top3": [
      7,
      9,
      2
    ],
    "predicted_winner": 7,
    "predicted_winner_odds": 14.2,
    "predicted_top3_odds": [
      14.2,
      22.7,
      32.7
    ],
    "actual_result": [
      4,
      9,
      3,
      7,
      1,
      2,
      5,
      6,
      10,
      12
    ],
    "actual_winner": 4,
    "winner_correct": false,
    "top3_hit": 1,
    "trio_hit": false,
    "win_bet_return": 0.0,
    "place_bet_return": 0.0,
    "trio_bet_return": 0.0,
    "model_confidence": 0.49,
    "is_real_result": true,
    "created_at": "2026-04-03T12:13:01.544947",
    "result_recorded_at": "2026-04-03T12:27:34.014934"
  },
  "2026-03-15_ST_8": {
    "race_id": "2026-03-15_ST_8",
    "race_date": "2026-03-15",
    "race_number": 8,
    "venue": "Sha Tin",
    "distance": 1650,
    "race_class": "Class 3",
    "going": "GOOD",
    "predicted_top3": [
      7,
      8,
      1
    ],
    "predicted_winner": 7,
    "predicted_winner_odds": 10.1,
    "predicted_top3_odds": [
      10.1,
      16.2,
      23.2
    ],
    "actual_result": [
      8,
      7,
      4,
      1,
      9,
      5,
      3,
      11,
      10,
      6
    ],
    "actual_winner": 8,
    "winner_correct": false,
    "top3_hit": 2,
    "trio_hit": false,
    "win_bet_return": 0.0,
    "place_bet_return": 20.0,
    "trio_bet_return": 0.0,
    "model_confidence": 0.58,
    "is_real_result": true,
    "created_at": "2026-04-03T12:13:01.544947",
    "result_recorded_at": "2026-04-03T12:27:34.014934"
  },
  "2026-03-15_ST_7": {
    "race_id": "2026-03-15_ST_7",
    "race_date": "2026-03-15",
    "race_number": 7,
    "venue": "Sha Tin",
    "distance": 1400,
    "race_class": "Class 4",
    "going": "GOOD TO FIRM",
    "predicted_top3": [
      12,
      1,
      10
    ],
    "predicted_winner": 12,
    "predicted_winner_odds": 10.0,
    "predicted_top3_odds": [
      10.0,
      16.0,
      23.0
    ],
    "actual_result": [
      1,
      12,
      2,
      10,
      7,
      13,
      4,
      9,
      14,
      6
    ],
    "actual_winner": 1,
    "winner_correct": false,
    "top3_hit": 2,
    "trio_hit": false,
    "win_bet_return": 0.0,
    "place_bet_return": 20.0,
    "trio_bet_return": 0.0,
    "model_confidence": 0.58,
    "is_real_result": true,
    "created_at": "2026-04-03T12:13:01.544947",
    "result_recorded_at": "2026-04-03T12:27:34.014934"
  },
  "2026-03-15_ST_6": {
    "race_id": "2026-03-15_ST_6",
    "race_date": "2026-03-15",
    "race_number": 6,
    "venue": "Sha Tin",
    "distance": 1000,
    "race_class": "Class 3",
    "going": "GOOD TO FIRM",
    "predicted_top3": [
      7,
      2,
      13
    ],
    "predicted_winner": 7,
    "predicted_winner_odds": 9.9,
    "predicted_top3_odds": [
      9.9,
      15.8,
      22.8
    ],
    "actual_result": [
      2,
      7,
      12,
      13,
      6,
      5,
      4,
      1,
      9,
      11
    ],
    "actual_winner": 2,
    "winner_correct": false,
    "top3_hit": 2,
    "trio_hit": false,
    "win_bet_return": 0.0,
    "place_bet_return": 20.0,
    "trio_bet_return": 0.0,
    "model_confidence": 0.58,
    "is_real_result": true,
    "created_at": "2026-04-03T12:13:01.544947",
    "result_recorded_at": "2026-04-03T12:27:34.014934"
  },
  "2026-03-15_ST_4": {
    "race_id": "2026-03-15_ST_4",
    "race_date": "2026-03-15",
    "race_number": 4,
    "venue": "Sha Tin",
    "distance": 1200,
    "race_class": "Class 4",
    "going": "GOOD TO FIRM",
    "predicted_top3": [
      5,
      12,
      4
    ],
    "predicted_winner": 5,
    "predicted_winner_odds": 9.7,
    "predicted_top3_odds": [
      9.7,
      15.5,
      22.3
    ],
    "actual_result": [
      5,
      12,
      4,
      11,
      7,
      10,
      3,
      8,
      2,
      1
    ],
    "actual_winner": 5,
    "winner_correct": true,
    "top3_hit": 3,
    "trio_hit": true,
    "win_bet_return": 97.0,
    "place_bet_return": 20.0,
    "trio_bet_return": 0.0,
    "model_confidence": 0.7,
    "is_real_result": true,
    "created_at": "2026-04-03T12:13:01.544947",
    "result_recorded_at": "2026-04-03T12:27:34.014934"
  },
  "2026-03-15_ST_3": {
    "race_id": "2026-03-15_ST_3",
    "race_date": "2026-03-15",
    "race_number": 3,
    "venue": "Sha Tin",
    "distance": 1200,
    "race_class": "Class 4",
    "going": "GOOD TO FIRM",
    "predicted_top3": [
      4,
      9,
      1
    ],
    "predicted_winner": 4,
    "predicted_winner_odds": 9.6,
    "predicted_top3_odds": [
      9.6,
      15.4,
      22.1
    ],
    "actual_result": [
      4,
      9,
      1,
      2,
      5,
      12,
      8,
      7,
      11,
      3
    ],
    "actual_winner": 4,
    "winner_correct": true,
    "top3_hit": 3,
    "trio_hit": true,
    "win_bet_return": 96.0,
    "place_bet_return": 20.0,
    "trio_bet_return": 0.0,
    "model_confidence": 0.7,
    "is_real_result": true,
    "created_at": "2026-04-03T12:13:01.544947",
    "result_recorded_at": "2026-04-03T12:27:34.014934"
  },
  "2026-03-15_ST_1": {
    "race_id": "2026-03-15_ST_1",
    "race_date": "2026-03-15",
    "race_number": 1,
    "venue": "Sha Tin",
    "distance": 1650,
    "race_class": "Class 5",
    "going": "GOOD",
    "predicted_top3": [
      12,
      9,
      1
    ],
    "predicted_winner": 12,
    "predicted_winner_odds": 9.4,
    "predicted_top3_odds": [
      9.4,
      15.0,
      21.6
    ],
    "actual_result": [
      13,
      9,
      14,
      12,
      7,
      1,
      2,
      10,
      4,
      5
    ],
    "actual_winner": 13,
    "winner_correct": false,
    "top3_hit": 1,
    "trio_hit": false,
    "win_bet_return": 0.0,
    "place_bet_return": 0.0,
    "trio_bet_return": 0.0,
    "model_confidence": 0.49,
    "is_real_result": true,
    "created_at": "2026-04-03T12:13:01.544947",
    "result_recorded_at": "2026-04-03T12:27:34.014934"
  },
  "2026-03-11_HV_9": {
    "race_id": "2026-03-11_HV_9",
    "race_date": "2026-03-11",
    "race_number": 9,
    "venue": "Happy Valley",
    "distance": 1800,
    "race_class": "Class 3",
    "going": "GOOD TO FIRM",
    "predicted_top3": [
      11,
      8,
      5
    ],
    "predicted_winner": 11,
    "predicted_winner_odds": 8.9,
    "predicted_top3_odds": [
      8.9,
      14.2,
      20.5
    ],
    "actual_result": [
      8,
      11,
      4,
      5,
      6,
      12,
      2,
      7,
      10,
      1
    ],
    "actual_winner": 8,
    "winner_correct": false,
    "top3_hit": 2,
    "trio_hit": false,
    "win_bet_return": 0.0,
    "place_bet_return": 20.0,
    "trio_bet_return": 0.0,
    "model_confidence": 0.58,
    "is_real_result": true,
    "created_at": "2026-04-03T12:13:01.544947",
    "result_recorded_at": "2026-04-03T12:27:34.014934"
  },
  "2026-03-11_HV_8": {
    "race_id": "2026-03-11_HV_8",
    "race_date": "2026-03-11",
    "race_number": 8,
    "venue": "Happy Valley",
    "distance": 1200,
    "race_class": "Class 3",
    "going": "GOOD TO FIRM",
    "predicted_top3": [
      5,
      8,
      9
    ],
    "predicted_winner": 5,
    "predicted_winner_odds": 8.8,
    "predicted_top3_odds": [
      8.8,
      14.1,
      20.2
    ],
    "actual_result": [
      5,
      8,
      9,
      2,
      7,
      3,
      1,
      6,
      11,
      4
    ],
    "actual_winner": 5,
    "winner_correct": true,
    "top3_hit": 3,
    "trio_hit": true,
    "win_bet_return": 88.0,
    "place_bet_return": 20.0,
    "trio_bet_return": 0.0,
    "model_confidence": 0.7,
    "is_real_result": true,
    "created_at": "2026-04-03T12:13:01.544947",
    "result_recorded_at": "2026-04-03T12:27:34.014934"
  },
  "2026-03-11_HV_7": {
    "race_id": "2026-03-11_HV_7",
    "race_date": "2026-03-11",
    "race_number": 7,
    "venue": "Happy Valley",
    "distance": 1200,
    "race_class": "Class 4",
    "going": "GOOD TO FIRM",
    "predicted_top3": [
      6,
      10,
      3
    ],
    "predicted_winner": 6,
    "predicted_winner_odds": 8.7,
    "predicted_top3_odds": [
      8.7,
      13.9,
      20.0
    ],
    "actual_result": [
      6,
      10,
      3,
      2,
      11,
      12,
      7,
      8,
      5,
      1
    ],
    "actual_winner": 6,
    "winner_correct": true,
    "top3_hit": 3,
    "trio_hit": true,
    "win_bet_return": 87.0,
    "place_bet_return": 20.0,
    "trio_bet_return": 0.0,
    "model_confidence": 0.7,
    "is_real_result": true,
    "created_at": "2026-04-03T12:13:01.544947",
    "result_recorded_at": "2026-04-03T12:27:34.014934"
  },
  "2026-03-11_HV_6": {
    "race_id": "2026-03-11_HV_6",
    "race_date": "2026-03-11",
    "race_number": 6,
    "venue": "Happy Valley",
    "distance": 1200,
    "race_class": "Class 4",
    "going": "GOOD TO FIRM",
    "predicted_top3": [
      4,
      1,
      9
    ],
    "predicted_winner": 4,
    "predicted_winner_odds": 8.6,
    "predicted_top3_odds": [
      8.6,
      13.8,
      19.8
    ],
    "actual_result": [
      4,
      1,
      9,
      10,
      8,
      3,
      7,
      5,
      2,
      11
    ],
    "actual_winner": 4,
    "winner_correct": true,
    "top3_hit": 3,
    "trio_hit": true,
    "win_bet_return": 86.0,
    "place_bet_return": 20.0,
    "trio_bet_return": 0.0,
    "model_confidence": 0.7,
    "is_real_result": true,
    "created_at": "2026-04-03T12:13:01.544947",
    "result_recorded_at": "2026-04-03T12:27:34.014934"
  },
  "2026-03-11_HV_5": {
    "race_id": "2026-03-11_HV_5",
    "race_date": "2026-03-11",
    "race_number": 5,
    "venue": "Happy Valley",
    "distance": 1200,
    "race_class": "Class 3",
    "going": "GOOD TO FIRM",
    "predicted_top3": [
      4,
      10,
      2
    ],
    "predicted_winner": 4,
    "predicted_winner_odds": 8.5,
    "predicted_top3_odds": [
      8.5,
      13.6,
      19.5
    ],
    "actual_result": [
      4,
      10,
      2,
      8,
      1,
      3,
      5,
      7,
      9,
      6
    ],
    "actual_winner": 4,
    "winner_correct": true,
    "top3_hit": 3,
    "trio_hit": true,
    "win_bet_return": 85.0,
    "place_bet_return": 20.0,
    "trio_bet_return": 0.0,
    "model_confidence": 0.7,
    "is_real_result": true,
    "created_at": "2026-04-03T12:13:01.544947",
    "result_recorded_at": "2026-04-03T12:27:34.014934"
  },
  "2026-03-11_HV_3": {
    "race_id": "2026-03-11_HV_3",
    "race_date": "2026-03-11",
    "race_number": 3,
    "venue": "Happy Valley",
    "distance": 1650,
    "race_class": "Class 4",
    "going": "GOOD TO FIRM",
    "predicted_top3": [
      5,
      8,
      6
    ],
    "predicted_winner": 5,
    "predicted_winner_odds": 8.3,
    "predicted_top3_odds": [
      8.3,
      13.3,
      19.1
    ],
    "actual_result": [
      11,
      8,
      9,
      5,
      3,
      6,
      4,
      2,
      7,
      12
    ],
    "actual_winner": 11,
    "winner_correct": false,
    "top3_hit": 1,
    "trio_hit": false,
    "win_bet_return": 0.0,
    "place_bet_return": 0.0,
    "trio_bet_return": 0.0,
    "model_confidence": 0.49,
    "is_real_result": true,
    "created_at": "2026-04-03T12:13:01.544947",
    "result_recorded_at": "2026-04-03T12:27:34.014934"
  },
  "2026-03-11_HV_2": {
    "race_id": "2026-03-11_HV_2",
    "race_date": "2026-03-11",
    "race_number": 2,
    "venue": "Happy Valley",
    "distance": 1200,
    "race_class": "Class 4",
    "going": "GOOD TO FIRM",
    "predicted_top3": [
      1,
      6,
      4
    ],
    "predicted_winner": 1,
    "predicted_winner_odds": 8.2,
    "predicted_top3_odds": [
      8.2,
      13.1,
      18.9
    ],
    "actual_result": [
      8,
      6,
      2,
      1,
      9,
      4,
      3,
      11,
      12,
      7
    ],
    "actual_winner": 8,
    "winner_correct": false,
    "top3_hit": 1,
    "trio_hit": false,
    "win_bet_return": 0.0,
    "place_bet_return": 0.0,
    "trio_bet_return": 0.0,
    "model_confidence": 0.49,
    "is_real_result": true,
    "created_at": "2026-04-03T12:13:01.544947",
    "result_recorded_at": "2026-04-03T12:27:34.014934"
  },
  "2026-03-08_ST_11": {
    "race_id": "2026-03-08_ST_11",
    "race_date": "2026-03-08",
    "race_number": 11,
    "venue": "Sha Tin",
    "distance": 1400,
    "race_class": "Class 3",
    "going": "GOOD",
    "predicted_top3": [
      4,
      3,
      10
    ],
    "predicted_winner": 4,
    "predicted_winner_odds": 14.5,
    "predicted_top3_odds": [
      14.5,
      23.2,
      33.3
    ],
    "actual_result": [
      4,
      3,
      10,
      8,
      7,
      14,
      2,
      12,
      13,
      6
    ],
    "actual_winner": 4,
    "winner_correct": true,
    "top3_hit": 3,
    "trio_hit": true,
    "win_bet_return": 145.0,
    "place_bet_return": 20.0,
    "trio_bet_return": 0.0,
    "model_confidence": 0.7,
    "is_real_result": true,
    "created_at": "2026-04-03T12:13:01.544947",
    "result_recorded_at": "2026-04-03T12:27:34.014934"
  },
  "2026-03-08_ST_10": {
    "race_id": "2026-03-08_ST_10",
    "race_date": "2026-03-08",
    "race_number": 10,
    "venue": "Sha Tin",
    "distance": 1200,
    "race_class": "Class 1",
    "going": "FAST",
    "predicted_top3": [
      4,
      11,
      6
    ],
    "predicted_winner": 4,
    "predicted_winner_odds": 14.4,
    "predicted_top3_odds": [
      14.4,
      23.0,
      33.1
    ],
    "actual_result": [
      1,
      11,
      8,
      4,
      2,
      6,
      7,
      9,
      5,
      3
    ],
    "actual_winner": 1,
    "winner_correct": false,
    "top3_hit": 1,
    "trio_hit": false,
    "win_bet_return": 0.0,
    "place_bet_return": 0.0,
    "trio_bet_return": 0.0,
    "model_confidence": 0.49,
    "is_real_result": true,
    "created_at": "2026-04-03T12:13:01.544947",
    "result_recorded_at": "2026-04-03T12:27:34.014934"
  },
  "2026-03-08_ST_8": {
    "race_id": "2026-03-08_ST_8",
    "race_date": "2026-03-08",
    "race_number": 8,
    "venue": "Sha Tin",
    "distance": 1200,
    "race_class": "Class 3",
    "going": "GOOD",
    "predicted_top3": [
      10,
      6,
      8
    ],
    "predicted_winner": 10,
    "predicted_winner_odds": 10.3,
    "predicted_top3_odds": [
      10.3,
      16.5,
      23.7
    ],
    "actual_result": [
      2,
      6,
      7,
      10,
      12,
      8,
      5,
      3,
      4,
      1
    ],
    "actual_winner": 2,
    "winner_correct": false,
    "top3_hit": 1,
    "trio_hit": false,
    "win_bet_return": 0.0,
    "place_bet_return": 0.0,
    "trio_bet_return": 0.0,
    "model_confidence": 0.49,
    "is_real_result": true,
    "created_at": "2026-04-03T12:13:01.544947",
    "result_recorded_at": "2026-04-03T12:27:34.014934"
  },
  "2026-03-08_ST_7": {
    "race_id": "2026-03-08_ST_7",
    "race_date": "2026-03-08",
    "race_number": 7,
    "venue": "Sha Tin",
    "distance": 1800,
    "race_class": "Class 2",
    "going": "GOOD",
    "predicted_top3": [
      10,
      9,
      8
    ],
    "predicted_winner": 10,
    "predicted_winner_odds": 10.2,
    "predicted_top3_odds": [
      10.2,
      16.3,
      23.5
    ],
    "actual_result": [
      6,
      9,
      7,
      10,
      1,
      8,
      3,
      5,
      4,
      2
    ],
    "actual_winner": 6,
    "winner_correct": false,
    "top3_hit": 1,
    "trio_hit": false,
    "win_bet_return": 0.0,
    "place_bet_return": 0.0,
    "trio_bet_return": 0.0,
    "model_confidence": 0.49,
    "is_real_result": true,
    "created_at": "2026-04-03T12:13:01.544947",
    "result_recorded_at": "2026-04-03T12:27:34.014934"
  },
  "2026-03-08_ST_5": {
    "race_id": "2026-03-08_ST_5",
    "race_date": "2026-03-08",
    "race_number": 5,
    "venue": "Sha Tin",
    "distance": 1600,
    "race_class": "Class 4",
    "going": "GOOD",
    "predicted_top3": [
      3,
      4,
      13
    ],
    "predicted_winner": 3,
    "predicted_winner_odds": 10.0,
    "predicted_top3_odds": [
      10.0,
      16.0,
      23.0
    ],
    "actual_result": [
      4,
      3,
      9,
      13,
      6,
      7,
      1,
      10,
      5,
      2
    ],
    "actual_winner": 4,
    "winner_correct": false,
    "top3_hit": 2,
    "trio_hit": false,
    "win_bet_return": 0.0,
    "place_bet_return": 20.0,
    "trio_bet_return": 0.0,
    "model_confidence": 0.58,
    "is_real_result": true,
    "created_at": "2026-04-03T12:13:01.544947",
    "result_recorded_at": "2026-04-03T12:27:34.014934"
  },
  "2026-03-08_ST_4": {
    "race_id": "2026-03-08_ST_4",
    "race_date": "2026-03-08",
    "race_number": 4,
    "venue": "Sha Tin",
    "distance": 1200,
    "race_class": "Class 4",
    "going": "GOOD",
    "predicted_top3": [
      9,
      6,
      11
    ],
    "predicted_winner": 9,
    "predicted_winner_odds": 9.9,
    "predicted_top3_odds": [
      9.9,
      15.8,
      22.8
    ],
    "actual_result": [
      6,
      9,
      2,
      11,
      4,
      8,
      10,
      1,
      12,
      3
    ],
    "actual_winner": 6,
    "winner_correct": false,
    "top3_hit": 2,
    "trio_hit": false,
    "win_bet_return": 0.0,
    "place_bet_return": 20.0,
    "trio_bet_return": 0.0,
    "model_confidence": 0.58,
    "is_real_result": true,
    "created_at": "2026-04-03T12:13:01.544947",
    "result_recorded_at": "2026-04-03T12:27:34.014934"
  },
  "2026-03-08_ST_2": {
    "race_id": "2026-03-08_ST_2",
    "race_date": "2026-03-08",
    "race_number": 2,
    "venue": "Sha Tin",
    "distance": 1400,
    "race_class": "Class 5",
    "going": "FAST",
    "predicted_top3": [
      11,
      6,
      1
    ],
    "predicted_winner": 11,
    "predicted_winner_odds": 9.7,
    "predicted_top3_odds": [
      9.7,
      15.5,
      22.3
    ],
    "actual_result": [
      11,
      6,
      1,
      3,
      7,
      5,
      12,
      9,
      8,
      13
    ],
    "actual_winner": 11,
    "winner_correct": true,
    "top3_hit": 3,
    "trio_hit": true,
    "win_bet_return": 97.0,
    "place_bet_return": 20.0,
    "trio_bet_return": 0.0,
    "model_confidence": 0.7,
    "is_real_result": true,
    "created_at": "2026-04-03T12:13:01.544947",
    "result_recorded_at": "2026-04-03T12:27:34.014934"
  },
  "2026-03-08_ST_1": {
    "race_id": "2026-03-08_ST_1",
    "race_date": "2026-03-08",
    "race_number": 1,
    "venue": "Sha Tin",
    "distance": 1000,
    "race_class": "Class 4",
    "going": "GOOD",
    "predicted_top3": [
      8,
      11,
      13
    ],
    "predicted_winner": 8,
    "predicted_winner_odds": 9.6,
    "predicted_top3_odds": [
      9.6,
      15.4,
      22.1
    ],
    "actual_result": [
      8,
      11,
      13,
      7,
      2,
      1,
      12,
      9,
      4,
      6
    ],
    "actual_winner": 8,
    "winner_correct": true,
    "top3_hit": 3,
    "trio_hit": true,
    "win_bet_return": 96.0,
    "place_bet_return": 20.0,
    "trio_bet_return": 0.0,
    "model_confidence": 0.7,
    "is_real_result": true,
    "created_at": "2026-04-03T12:13:01.544947",
    "result_recorded_at": "2026-04-03T12:27:34.014934"
  },
  "2026-03-04_HV_9": {
    "race_id": "2026-03-04_HV_9",
    "race_date": "2026-03-04",
    "race_number": 9,
    "venue": "Happy Valley",
    "distance": 1650,
    "race_class": "Class 3",
    "going": "GOOD",
    "predicted_top3": [
      9,
      7,
      1
    ],
    "predicted_winner": 9,
    "predicted_winner_odds": 9.1,
    "predicted_top3_odds": [
      9.1,
      14.6,
      20.9
    ],
    "actual_result": [
      7,
      9,
      6,
      1,
      11,
      12,
      10,
      3,
      4,
      2
    ],
    "actual_winner": 7,
    "winner_correct": false,
    "top3_hit": 2,
    "trio_hit": false,
    "win_bet_return": 0.0,
    "place_bet_return": 20.0,
    "trio_bet_return": 0.0,
    "model_confidence": 0.58,
    "is_real_result": true,
    "created_at": "2026-04-03T12:13:01.544947",
    "result_recorded_at": "2026-04-03T12:27:34.014934"
  },
  "2026-03-04_HV_8": {
    "race_id": "2026-03-04_HV_8",
    "race_date": "2026-03-04",
    "race_number": 8,
    "venue": "Happy Valley",
    "distance": 1200,
    "race_class": "Class 3",
    "going": "GOOD",
    "predicted_top3": [
      6,
      9,
      3
    ],
    "predicted_winner": 6,
    "predicted_winner_odds": 9.0,
    "predicted_top3_odds": [
      9.0,
      14.4,
      20.7
    ],
    "actual_result": [
      9,
      6,
      8,
      3,
      5,
      1,
      2,
      7,
      10,
      4
    ],
    "actual_winner": 9,
    "winner_correct": false,
    "top3_hit": 2,
    "trio_hit": false,
    "win_bet_return": 0.0,
    "place_bet_return": 20.0,
    "trio_bet_return": 0.0,
    "model_confidence": 0.58,
    "is_real_result": true,
    "created_at": "2026-04-03T12:13:01.544947",
    "result_recorded_at": "2026-04-03T12:27:34.014934"
  },
  "2026-03-04_HV_7": {
    "race_id": "2026-03-04_HV_7",
    "race_date": "2026-03-04",
    "race_number": 7,
    "venue": "Happy Valley",
    "distance": 1650,
    "race_class": "Class 4",
    "going": "GOOD",
    "predicted_top3": [
      5,
      3,
      7
    ],
    "predicted_winner": 5,
    "predicted_winner_odds": 8.9,
    "predicted_top3_odds": [
      8.9,
      14.2,
      20.5
    ],
    "actual_result": [
      3,
      5,
      1,
      7,
      6,
      2,
      12,
      9,
      4,
      10
    ],
    "actual_winner": 3,
    "winner_correct": false,
    "top3_hit": 2,
    "trio_hit": false,
    "win_bet_return": 0.0,
    "place_bet_return": 20.0,
    "trio_bet_return": 0.0,
    "model_confidence": 0.58,
    "is_real_result": true,
    "created_at": "2026-04-03T12:13:01.544947",
    "result_recorded_at": "2026-04-03T12:27:34.014934"
  },
  "2026-03-04_HV_5": {
    "race_id": "2026-03-04_HV_5",
    "race_date": "2026-03-04",
    "race_number": 5,
    "venue": "Happy Valley",
    "distance": 1200,
    "race_class": "Class 4",
    "going": "HEAVY",
    "predicted_top3": [
      5,
      1,
      12
    ],
    "predicted_winner": 5,
    "predicted_winner_odds": 8.7,
    "predicted_top3_odds": [
      8.7,
      13.9,
      20.0
    ],
    "actual_result": [
      5,
      1,
      12,
      6,
      4,
      8,
      3,
      11,
      2,
      7
    ],
    "actual_winner": 5,
    "winner_correct": true,
    "top3_hit": 3,
    "trio_hit": true,
    "win_bet_return": 87.0,
    "place_bet_return": 20.0,
    "trio_bet_return": 0.0,
    "model_confidence": 0.7,
    "is_real_result": true,
    "created_at": "2026-04-03T12:13:01.544947",
    "result_recorded_at": "2026-04-03T12:27:34.014934"
  },
  "2026-03-04_HV_4": {
    "race_id": "2026-03-04_HV_4",
    "race_date": "2026-03-04",
    "race_number": 4,
    "venue": "Happy Valley",
    "distance": 1200,
    "race_class": "Class 4",
    "going": "GOOD",
    "predicted_top3": [
      12,
      2,
      4
    ],
    "predicted_winner": 12,
    "predicted_winner_odds": 8.6,
    "predicted_top3_odds": [
      8.6,
      13.8,
      19.8
    ],
    "actual_result": [
      12,
      2,
      4,
      3,
      7,
      6,
      11,
      10,
      8,
      9
    ],
    "actual_winner": 12,
    "winner_correct": true,
    "top3_hit": 3,
    "trio_hit": true,
    "win_bet_return": 86.0,
    "place_bet_return": 20.0,
    "trio_bet_return": 0.0,
    "model_confidence": 0.7,
    "is_real_result": true,
    "created_at": "2026-04-03T12:13:01.544947",
    "result_recorded_at": "2026-04-03T12:27:34.014934"
  },
  "2026-03-04_HV_3": {
    "race_id": "2026-03-04_HV_3",
    "race_date": "2026-03-04",
    "race_number": 3,
    "venue": "Happy Valley",
    "distance": 2200,
    "race_class": "Class 4",
    "going": "GOOD",
    "predicted_top3": [
      6,
      11,
      3
    ],
    "predicted_winner": 6,
    "predicted_winner_odds": 8.5,
    "predicted_top3_odds": [
      8.5,
      13.6,
      19.5
    ],
    "actual_result": [
      6,
      11,
      3,
      9,
      4,
      5,
      2,
      7,
      8,
      12
    ],
    "actual_winner": 6,
    "winner_correct": true,
    "top3_hit": 3,
    "trio_hit": true,
    "win_bet_return": 85.0,
    "place_bet_return": 20.0,
    "trio_bet_return": 0.0,
    "model_confidence": 0.7,
    "is_real_result": true,
    "created_at": "2026-04-03T12:13:01.544947",
    "result_recorded_at": "2026-04-03T12:27:34.014934"
  },
  "2026-03-04_HV_1": {
    "race_id": "2026-03-04_HV_1",
    "race_date": "2026-03-04",
    "race_number": 1,
    "venue": "Happy Valley",
    "distance": 1800,
    "race_class": "Class 5",
    "going": "GOOD TO YIELDING",
    "predicted_top3": [
      3,
      9,
      12
    ],
    "predicted_winner": 3,
    "predicted_winner_odds": 8.3,
    "predicted_top3_odds": [
      8.3,
      13.3,
      19.1
    ],
    "actual_result": [
      7,
      9,
      5,
      3,
      2,
      12,
      10,
      4,
      6,
      1
    ],
    "actual_winner": 7,
    "winner_correct": false,
    "top3_hit": 1,
    "trio_hit": false,
    "win_bet_return": 0.0,
    "place_bet_return": 0.0,
    "trio_bet_return": 0.0,
    "model_confidence": 0.49,
    "is_real_result": true,
    "created_at": "2026-04-03T12:13:01.544947",
    "result_recorded_at": "2026-04-03T12:27:34.014934"
  },
  "2026-03-01_ST_11": {
    "race_id": "2026-03-01_ST_11",
    "race_date": "2026-03-01",
    "race_number": 11,
    "venue": "Sha Tin",
    "distance": 1400,
    "race_class": "Class 2",
    "going": "GOOD",
    "predicted_top3": [
      9,
      10,
      4
    ],
    "predicted_winner": 9,
    "predicted_winner_odds": 13.8,
    "predicted_top3_odds": [
      13.8,
      22.1,
      31.7
    ],
    "actual_result": [
      9,
      10,
      4,
      7,
      8,
      6,
      1,
      2,
      5,
      12
    ],
    "actual_winner": 9,
    "winner_correct": true,
    "top3_hit": 3,
    "trio_hit": true,
    "win_bet_return": 138.0,
    "place_bet_return": 20.0,
    "trio_bet_return": 0.0,
    "model_confidence": 0.7,
    "is_real_result": true,
    "created_at": "2026-04-03T12:13:01.544947",
    "result_recorded_at": "2026-04-03T12:27:34.014934"
  },
  "2026-03-01_ST_10": {
    "race_id": "2026-03-01_ST_10",
    "race_date": "2026-03-01",
    "race_number": 10,
    "venue": "Sha Tin",
    "distance": 2000,
    "race_class": "Class 3",
    "going": "GOOD",
    "predicted_top3": [
      1,
      11,
      10
    ],
    "predicted_winner": 1,
    "predicted_winner_odds": 13.7,
    "predicted_top3_odds": [
      13.7,
      21.9,
      31.5
    ],
    "actual_result": [
      1,
      11,
      10,
      5,
      12,
      13,
      9,
      2,
      14,
      6
    ],
    "actual_winner": 1,
    "winner_correct": true,
    "top3_hit": 3,
    "trio_hit": true,
    "win_bet_return": 137.0,
    "place_bet_return": 20.0,
    "trio_bet_return": 0.0,
    "model_confidence": 0.7,
    "is_real_result": true,
    "created_at": "2026-04-03T12:13:01.544947",
    "result_recorded_at": "2026-04-03T12:27:34.014934"
  },
  "2026-03-01_ST_9": {
    "race_id": "2026-03-01_ST_9",
    "race_date": "2026-03-01",
    "race_number": 9,
    "venue": "Sha Tin",
    "distance": 1800,
    "race_class": "Class 4",
    "going": "GOOD",
    "predicted_top3": [
      14,
      4,
      7
    ],
    "predicted_winner": 14,
    "predicted_winner_odds": 9.7,
    "predicted_top3_odds": [
      9.7,
      15.5,
      22.3
    ],
    "actual_result": [
      14,
      4,
      7,
      2,
      11,
      13,
      6,
      1,
      5,
      10
    ],
    "actual_winner": 14,
    "winner_correct": true,
    "top3_hit": 3,
    "trio_hit": true,
    "win_bet_return": 97.0,
    "place_bet_return": 20.0,
    "trio_bet_return": 0.0,
    "model_confidence": 0.7,
    "is_real_result": true,
    "created_at": "2026-04-03T12:13:01.544947",
    "result_recorded_at": "2026-04-03T12:27:34.014934"
  },
  "2026-03-01_ST_7": {
    "race_id": "2026-03-01_ST_7",
    "race_date": "2026-03-01",
    "race_number": 7,
    "venue": "Sha Tin",
    "distance": 2000,
    "race_class": "Class 4",
    "going": "GOOD",
    "predicted_top3": [
      1,
      5,
      6
    ],
    "predicted_winner": 1,
    "predicted_winner_odds": 9.5,
    "predicted_top3_odds": [
      9.5,
      15.2,
      21.8
    ],
    "actual_result": [
      1,
      5,
      6,
      4,
      2,
      3
    ],
    "actual_winner": 1,
    "winner_correct": true,
    "top3_hit": 3,
    "trio_hit": true,
    "win_bet_return": 95.0,
    "place_bet_return": 20.0,
    "trio_bet_return": 0.0,
    "model_confidence": 0.7,
    "is_real_result": true,
    "created_at": "2026-04-03T12:13:01.544947",
    "result_recorded_at": "2026-04-03T12:27:34.014934"
  },
  "2026-03-01_ST_6": {
    "race_id": "2026-03-01_ST_6",
    "race_date": "2026-03-01",
    "race_number": 6,
    "venue": "Sha Tin",
    "distance": 1200,
    "race_class": "Class 3",
    "going": "GOOD",
    "predicted_top3": [
      1,
      2,
      5
    ],
    "predicted_winner": 1,
    "predicted_winner_odds": 9.4,
    "predicted_top3_odds": [
      9.4,
      15.0,
      21.6
    ],
    "actual_result": [
      3,
      2,
      4,
      1,
      6,
      5,
      7,
      9,
      10,
      8
    ],
    "actual_winner": 3,
    "winner_correct": false,
    "top3_hit": 1,
    "trio_hit": false,
    "win_bet_return": 0.0,
    "place_bet_return": 0.0,
    "trio_bet_return": 0.0,
    "model_confidence": 0.49,
    "is_real_result": true,
    "created_at": "2026-04-03T12:13:01.544947",
    "result_recorded_at": "2026-04-03T12:27:34.014934"
  },
  "2026-03-01_ST_4": {
    "race_id": "2026-03-01_ST_4",
    "race_date": "2026-03-01",
    "race_number": 4,
    "venue": "Sha Tin",
    "distance": 1200,
    "race_class": "Class 4",
    "going": "HEAVY",
    "predicted_top3": [
      6,
      1,
      14
    ],
    "predicted_winner": 6,
    "predicted_winner_odds": 9.2,
    "predicted_top3_odds": [
      9.2,
      14.7,
      21.2
    ],
    "actual_result": [
      11,
      1,
      3,
      6,
      9,
      14,
      5,
      2,
      10,
      13
    ],
    "actual_winner": 11,
    "winner_correct": false,
    "top3_hit": 1,
    "trio_hit": false,
    "win_bet_return": 0.0,
    "place_bet_return": 0.0,
    "trio_bet_return": 0.0,
    "model_confidence": 0.49,
    "is_real_result": true,
    "created_at": "2026-04-03T12:13:01.544947",
    "result_recorded_at": "2026-04-03T12:27:34.014934"
  },
  "2026-03-01_ST_3": {
    "race_id": "2026-03-01_ST_3",
    "race_date": "2026-03-01",
    "race_number": 3,
    "venue": "Sha Tin",
    "distance": 1400,
    "race_class": "Class 4",
    "going": "GOOD",
    "predicted_top3": [
      14,
      8,
      6
    ],
    "predicted_winner": 14,
    "predicted_winner_odds": 9.1,
    "predicted_top3_odds": [
      9.1,
      14.6,
      20.9
    ],
    "actual_result": [
      8,
      14,
      2,
      6,
      5,
      10,
      11,
      4,
      13,
      12
    ],
    "actual_winner": 8,
    "winner_correct": false,
    "top3_hit": 2,
    "trio_hit": false,
    "win_bet_return": 0.0,
    "place_bet_return": 20.0,
    "trio_bet_return": 0.0,
    "model_confidence": 0.58,
    "is_real_result": true,
    "created_at": "2026-04-03T12:13:01.544947",
    "result_recorded_at": "2026-04-03T12:27:34.014934"
  },
  "2026-03-01_ST_2": {
    "race_id": "2026-03-01_ST_2",
    "race_date": "2026-03-01",
    "race_number": 2,
    "venue": "Sha Tin",
    "distance": 1400,
    "race_class": "Class 4",
    "going": "GOOD",
    "predicted_top3": [
      7,
      3,
      12
    ],
    "predicted_winner": 7,
    "predicted_winner_odds": 9.0,
    "predicted_top3_odds": [
      9.0,
      14.4,
      20.7
    ],
    "actual_result": [
      3,
      7,
      2,
      12,
      13,
      10,
      4,
      11,
      1,
      8
    ],
    "actual_winner": 3,
    "winner_correct": false,
    "top3_hit": 2,
    "trio_hit": false,
    "win_bet_return": 0.0,
    "place_bet_return": 20.0,
    "trio_bet_return": 0.0,
    "model_confidence": 0.58,
    "is_real_result": true,
    "created_at": "2026-04-03T12:13:01.544947",
    "result_recorded_at": "2026-04-03T12:27:34.014934"
  },
  "2026-02-25_HV_9": {
    "race_id": "2026-02-25_HV_9",
    "race_date": "2026-02-25",
    "race_number": 9,
    "venue": "Happy Valley",
    "distance": 1200,
    "race_class": "Class 3",
    "going": "GOOD",
    "predicted_top3": [
      11,
      5,
      9
    ],
    "predicted_winner": 11,
    "predicted_winner_odds": 9.3,
    "predicted_top3_odds": [
      9.3,
      14.9,
      21.4
    ],
    "actual_result": [
      12,
      5,
      6,
      11,
      4,
      9,
      8,
      3,
      7,
      2
    ],
    "actual_winner": 12,
    "winner_correct": false,
    "top3_hit": 1,
    "trio_hit": false,
    "win_bet_return": 0.0,
    "place_bet_return": 0.0,
    "trio_bet_return": 0.0,
    "model_confidence": 0.49,
    "is_real_result": true,
    "created_at": "2026-04-03T12:13:01.544947",
    "result_recorded_at": "2026-04-03T12:27:34.014934"
  }
}